Workbook
Name AsOfDate: Assumptions!$C$4
Name DPD_From: Assumptions!$B$8:$B$14
Name DPD_Bucket: Assumptions!$C$8:$C$14
Name DPD_Class: Assumptions!$D$8:$D$14
Name DPD_NPA: Assumptions!$E$8:$E$14
Name DPD_Prov: Assumptions!$F$8:$F$14
Name CIBIL_From: Assumptions!$H$8:$H$11
Name CIBIL_Grade: Assumptions!$I$8:$I$11

Sheet Guide
B2: Loan Portfolio Risk Analytics
B3: Formula-driven credit-risk model for a synthetic retail & SME loan book (India / BFSI)
B5: SHEET | C5: WHAT IT DOES
B6: Dashboard | C6: Interactive KPIs & charts. Pick Region / Product in the yellow cells (C4, C5) — every figure, chart and the Top-10 table updates.
B7: Loans | C7: Loan-level book. Blue columns are raw inputs; black columns are formulas (EMI, outstanding, DPD bucket, asset class, provision, risk grade).
B8: Vintage | C8: Cohort analysis by disbursal quarter: count, disbursed, GNPA % — heat-mapped to spot bad vintages.
B9: EMI Calculator | C9: Standalone EMI tool with full amortization schedule (PMT / IPMT / PPMT) and principal-vs-interest chart.
B10: Assumptions | C10: As-of date, RBI-style asset-classification & provisioning table, CIBIL risk-grade bands. Edit here to re-run the model.
B11: Branches | C11: Branch master used to map each loan to City / Region via INDEX-MATCH.
B13: COLOUR KEY
B14: Blue text | C14: Hardcoded input — safe to edit.
B15: Black text | C15: Formula — do not overwrite.
B16: Green text | C16: Link pulled from another sheet.
B17: Yellow fill | C17: Key assumption / user selection.
B19: TECHNIQUES USED | C19: SUMIFS / COUNTIFS / SUMPRODUCT, INDEX-MATCH (exact & approximate), LARGE with tie-break keys, PMT / PV / IPMT / PPMT, EDATE, named ranges, data validation dropdowns, dynamic filter flag column, conditional formatting (data bars, colour scales, formula rules), Excel Tables, combo & doughnut charts, frozen panes, cell comments documenting assumptions.
B20: DISCLAIMER | C20: All data is synthetic (seeded random). Provisioning rates are simplified illustrations of RBI IRACP norms, not regulatory advice.

Sheet Dashboard
B2: Loan Portfolio Risk Dashboard
B3: ="Snapshot as of "&TEXT(AsOfDate,"dd-mmm-yyyy")&" | All amounts in ₹ Crore"
B4: Region | C4: All | D4: ◀ select filters
B5: Product | C5: All
B7: ACTIVE LOANS | C7: DISBURSED | D7: OUTSTANDING (AUM) | E7: GROSS NPA | F7: GNPA % | H7: TOTAL PROVISION | I7: NET NPA | J7: NNPA % | K7: PROVISION COVERAGE | L7: SMA (EARLY STRESS)
B8: =COUNTIFS(Loans!$X$2:$X$1001,1,Loans!$O$2:$O$1001,">0") | C8: =SUMIFS(Loans!$G$2:$G$1001,Loans!$X$2:$X$1001,1)/10^7 | D8: =SUMIFS(Loans!$O$2:$O$1001,Loans!$X$2:$X$1001,1)/10^7 | E8: =SUMIFS(Loans!$O$2:$O$1001,Loans!$X$2:$X$1001,1,Loans!$S$2:$S$1001,"Yes")/10^7 | F8: =IFERROR(E8/D8,0) | H8: =SUMIFS(Loans!$U$2:$U$1001,Loans!$X$2:$X$1001,1)/10^7 | I8: =E8-SUMIFS(Loans!$U$2:$U$1001,Loans!$X$2:$X$1001,1,Loans!$S$2:$S$1001,"Yes")/10^7 | J8: =IFERROR(I8/(D8-(E8-I8)),0) | K8: =IFERROR((E8-I8)/E8,0) | L8: =SUMIFS(Loans!$O$2:$O$1001,Loans!$X$2:$X$1001,1,Loans!$K$2:$K$1001,">0",Loans!$S$2:$S$1001,"No")/10^7
B10: WTD AVG RATE | C10: AVG CIBIL | D10: AVG TICKET (₹ Lakh) | E10: NPA ACCOUNTS | F10: OVERDUE AMT | H10: Traffic light: GNPA % > 5% turns red, 3–5% amber, < 3% green.
B11: =IFERROR(SUMPRODUCT(Loans!$X$2:$X$1001,Loans!$O$2:$O$1001,Loans!$H$2:$H$1001)/SUMPRODUCT(Loans!$X$2:$X$1001,Loans!$O$2:$O$1001),0) | C11: =IFERROR(AVERAGEIFS(Loans!$J$2:$J$1001,Loans!$X$2:$X$1001,1),0) | D11: =IFERROR(SUMIFS(Loans!$G$2:$G$1001,Loans!$X$2:$X$1001,1)/COUNTIFS(Loans!$X$2:$X$1001,1)/10^5,0) | E11: =COUNTIFS(Loans!$X$2:$X$1001,1,Loans!$S$2:$S$1001,"Yes") | F11: =SUMIFS(Loans!$P$2:$P$1001,Loans!$X$2:$X$1001,1)/10^7
B13: Book by DPD Bucket | H13: Performance by Product
B14: Bucket | C14: Accounts | D14: Outstanding | E14: % of Book | F14: Provision | H14: Product | I14: Outstanding | J14: GNPA | K14: GNPA % | L14: Wtd Rate
B15: =INDEX(DPD_Bucket,1) | C15: =COUNTIFS(Loans!$X$2:$X$1001,1,Loans!$Q$2:$Q$1001,B15,Loans!$O$2:$O$1001,">0") | D15: =SUMIFS(Loans!$O$2:$O$1001,Loans!$X$2:$X$1001,1,Loans!$Q$2:$Q$1001,B15)/10^7 | E15: =IFERROR(D15/$D$8,0) | F15: =SUMIFS(Loans!$U$2:$U$1001,Loans!$X$2:$X$1001,1,Loans!$Q$2:$Q$1001,B15)/10^7 | H15: Home Loan | I15: =SUMIFS(Loans!$O$2:$O$1001,Loans!$X$2:$X$1001,1,Loans!$E$2:$E$1001,H15)/10^7 | J15: =SUMIFS(Loans!$O$2:$O$1001,Loans!$X$2:$X$1001,1,Loans!$E$2:$E$1001,H15,Loans!$S$2:$S$1001,"Yes")/10^7 | K15: =IFERROR(J15/I15,0) | L15: =IFERROR(SUMPRODUCT(Loans!$X$2:$X$1001,--(Loans!$E$2:$E$1001=H15),Loans!$O$2:$O$1001,Loans!$H$2:$H$1001)/SUMPRODUCT(Loans!$X$2:$X$1001,--(Loans!$E$2:$E$1001=H15),Loans!$O$2:$O$1001),0)
B16: =INDEX(DPD_Bucket,2) | C16: =COUNTIFS(Loans!$X$2:$X$1001,1,Loans!$Q$2:$Q$1001,B16,Loans!$O$2:$O$1001,">0") | D16: =SUMIFS(Loans!$O$2:$O$1001,Loans!$X$2:$X$1001,1,Loans!$Q$2:$Q$1001,B16)/10^7 | E16: =IFERROR(D16/$D$8,0) | F16: =SUMIFS(Loans!$U$2:$U$1001,Loans!$X$2:$X$1001,1,Loans!$Q$2:$Q$1001,B16)/10^7 | H16: Auto Loan | I16: =SUMIFS(Loans!$O$2:$O$1001,Loans!$X$2:$X$1001,1,Loans!$E$2:$E$1001,H16)/10^7 | J16: =SUMIFS(Loans!$O$2:$O$1001,Loans!$X$2:$X$1001,1,Loans!$E$2:$E$1001,H16,Loans!$S$2:$S$1001,"Yes")/10^7 | K16: =IFERROR(J16/I16,0) | L16: =IFERROR(SUMPRODUCT(Loans!$X$2:$X$1001,--(Loans!$E$2:$E$1001=H16),Loans!$O$2:$O$1001,Loans!$H$2:$H$1001)/SUMPRODUCT(Loans!$X$2:$X$1001,--(Loans!$E$2:$E$1001=H16),Loans!$O$2:$O$1001),0)
B17: =INDEX(DPD_Bucket,3) | C17: =COUNTIFS(Loans!$X$2:$X$1001,1,Loans!$Q$2:$Q$1001,B17,Loans!$O$2:$O$1001,">0") | D17: =SUMIFS(Loans!$O$2:$O$1001,Loans!$X$2:$X$1001,1,Loans!$Q$2:$Q$1001,B17)/10^7 | E17: =IFERROR(D17/$D$8,0) | F17: =SUMIFS(Loans!$U$2:$U$1001,Loans!$X$2:$X$1001,1,Loans!$Q$2:$Q$1001,B17)/10^7 | H17: Personal Loan | I17: =SUMIFS(Loans!$O$2:$O$1001,Loans!$X$2:$X$1001,1,Loans!$E$2:$E$1001,H17)/10^7 | J17: =SUMIFS(Loans!$O$2:$O$1001,Loans!$X$2:$X$1001,1,Loans!$E$2:$E$1001,H17,Loans!$S$2:$S$1001,"Yes")/10^7 | K17: =IFERROR(J17/I17,0) | L17: =IFERROR(SUMPRODUCT(Loans!$X$2:$X$1001,--(Loans!$E$2:$E$1001=H17),Loans!$O$2:$O$1001,Loans!$H$2:$H$1001)/SUMPRODUCT(Loans!$X$2:$X$1001,--(Loans!$E$2:$E$1001=H17),Loans!$O$2:$O$1001),0)
B18: =INDEX(DPD_Bucket,4) | C18: =COUNTIFS(Loans!$X$2:$X$1001,1,Loans!$Q$2:$Q$1001,B18,Loans!$O$2:$O$1001,">0") | D18: =SUMIFS(Loans!$O$2:$O$1001,Loans!$X$2:$X$1001,1,Loans!$Q$2:$Q$1001,B18)/10^7 | E18: =IFERROR(D18/$D$8,0) | F18: =SUMIFS(Loans!$U$2:$U$1001,Loans!$X$2:$X$1001,1,Loans!$Q$2:$Q$1001,B18)/10^7 | H18: Business Loan | I18: =SUMIFS(Loans!$O$2:$O$1001,Loans!$X$2:$X$1001,1,Loans!$E$2:$E$1001,H18)/10^7 | J18: =SUMIFS(Loans!$O$2:$O$1001,Loans!$X$2:$X$1001,1,Loans!$E$2:$E$1001,H18,Loans!$S$2:$S$1001,"Yes")/10^7 | K18: =IFERROR(J18/I18,0) | L18: =IFERROR(SUMPRODUCT(Loans!$X$2:$X$1001,--(Loans!$E$2:$E$1001=H18),Loans!$O$2:$O$1001,Loans!$H$2:$H$1001)/SUMPRODUCT(Loans!$X$2:$X$1001,--(Loans!$E$2:$E$1001=H18),Loans!$O$2:$O$1001),0)
B19: =INDEX(DPD_Bucket,5) | C19: =COUNTIFS(Loans!$X$2:$X$1001,1,Loans!$Q$2:$Q$1001,B19,Loans!$O$2:$O$1001,">0") | D19: =SUMIFS(Loans!$O$2:$O$1001,Loans!$X$2:$X$1001,1,Loans!$Q$2:$Q$1001,B19)/10^7 | E19: =IFERROR(D19/$D$8,0) | F19: =SUMIFS(Loans!$U$2:$U$1001,Loans!$X$2:$X$1001,1,Loans!$Q$2:$Q$1001,B19)/10^7 | H19: Gold Loan | I19: =SUMIFS(Loans!$O$2:$O$1001,Loans!$X$2:$X$1001,1,Loans!$E$2:$E$1001,H19)/10^7 | J19: =SUMIFS(Loans!$O$2:$O$1001,Loans!$X$2:$X$1001,1,Loans!$E$2:$E$1001,H19,Loans!$S$2:$S$1001,"Yes")/10^7 | K19: =IFERROR(J19/I19,0) | L19: =IFERROR(SUMPRODUCT(Loans!$X$2:$X$1001,--(Loans!$E$2:$E$1001=H19),Loans!$O$2:$O$1001,Loans!$H$2:$H$1001)/SUMPRODUCT(Loans!$X$2:$X$1001,--(Loans!$E$2:$E$1001=H19),Loans!$O$2:$O$1001),0)
B20: =INDEX(DPD_Bucket,6) | C20: =COUNTIFS(Loans!$X$2:$X$1001,1,Loans!$Q$2:$Q$1001,B20,Loans!$O$2:$O$1001,">0") | D20: =SUMIFS(Loans!$O$2:$O$1001,Loans!$X$2:$X$1001,1,Loans!$Q$2:$Q$1001,B20)/10^7 | E20: =IFERROR(D20/$D$8,0) | F20: =SUMIFS(Loans!$U$2:$U$1001,Loans!$X$2:$X$1001,1,Loans!$Q$2:$Q$1001,B20)/10^7
B21: =INDEX(DPD_Bucket,7) | C21: =COUNTIFS(Loans!$X$2:$X$1001,1,Loans!$Q$2:$Q$1001,B21,Loans!$O$2:$O$1001,">0") | D21: =SUMIFS(Loans!$O$2:$O$1001,Loans!$X$2:$X$1001,1,Loans!$Q$2:$Q$1001,B21)/10^7 | E21: =IFERROR(D21/$D$8,0) | F21: =SUMIFS(Loans!$U$2:$U$1001,Loans!$X$2:$X$1001,1,Loans!$Q$2:$Q$1001,B21)/10^7
B22: Total | C22: =SUM(C15:C21) | D22: =SUM(D15:D21) | E22: =SUM(E15:E21) | F22: =SUM(F15:F21) | H22: Performance by Region
B23: =IF(ABS(D22-D8)<0.0001,"✔ Reconciles to AUM","✖ Check: bucket total ≠ AUM") | H23: Region | I23: Outstanding | J23: GNPA | K23: GNPA % | L23: Accounts
H24: North | I24: =SUMIFS(Loans!$O$2:$O$1001,Loans!$X$2:$X$1001,1,Loans!$D$2:$D$1001,H24)/10^7 | J24: =SUMIFS(Loans!$O$2:$O$1001,Loans!$X$2:$X$1001,1,Loans!$D$2:$D$1001,H24,Loans!$S$2:$S$1001,"Yes")/10^7 | K24: =IFERROR(J24/I24,0) | L24: =COUNTIFS(Loans!$X$2:$X$1001,1,Loans!$D$2:$D$1001,H24)
H25: South | I25: =SUMIFS(Loans!$O$2:$O$1001,Loans!$X$2:$X$1001,1,Loans!$D$2:$D$1001,H25)/10^7 | J25: =SUMIFS(Loans!$O$2:$O$1001,Loans!$X$2:$X$1001,1,Loans!$D$2:$D$1001,H25,Loans!$S$2:$S$1001,"Yes")/10^7 | K25: =IFERROR(J25/I25,0) | L25: =COUNTIFS(Loans!$X$2:$X$1001,1,Loans!$D$2:$D$1001,H25)
H26: East | I26: =SUMIFS(Loans!$O$2:$O$1001,Loans!$X$2:$X$1001,1,Loans!$D$2:$D$1001,H26)/10^7 | J26: =SUMIFS(Loans!$O$2:$O$1001,Loans!$X$2:$X$1001,1,Loans!$D$2:$D$1001,H26,Loans!$S$2:$S$1001,"Yes")/10^7 | K26: =IFERROR(J26/I26,0) | L26: =COUNTIFS(Loans!$X$2:$X$1001,1,Loans!$D$2:$D$1001,H26)
H27: West | I27: =SUMIFS(Loans!$O$2:$O$1001,Loans!$X$2:$X$1001,1,Loans!$D$2:$D$1001,H27)/10^7 | J27: =SUMIFS(Loans!$O$2:$O$1001,Loans!$X$2:$X$1001,1,Loans!$D$2:$D$1001,H27,Loans!$S$2:$S$1001,"Yes")/10^7 | K27: =IFERROR(J27/I27,0) | L27: =COUNTIFS(Loans!$X$2:$X$1001,1,Loans!$D$2:$D$1001,H27)
B29: Top 10 NPA Exposures (current filter)
B30: Rank | C30: Loan ID | D30: Customer | E30: Product | F30: Outstanding (₹) | H30: DPD | I30: Asset Class | J30: Branch | K30: CIBIL
B31: 1 | C31: =IF(LARGE(Loans!$Y$2:$Y$1001,B31)=0,"",INDEX(Loans!$A$2:$A$1001,MATCH(LARGE(Loans!$Y$2:$Y$1001,B31),Loans!$Y$2:$Y$1001,0))) | D31: =IF(C31="","",INDEX(Loans!$B$2:$B$1001,MATCH(LARGE(Loans!$Y$2:$Y$1001,B31),Loans!$Y$2:$Y$1001,0))) | E31: =IF(C31="","",INDEX(Loans!$E$2:$E$1001,MATCH(LARGE(Loans!$Y$2:$Y$1001,B31),Loans!$Y$2:$Y$1001,0))) | F31: =IF(C31="","",INDEX(Loans!$O$2:$O$1001,MATCH(LARGE(Loans!$Y$2:$Y$1001,B31),Loans!$Y$2:$Y$1001,0))) | H31: =IF(C31="","",INDEX(Loans!$K$2:$K$1001,MATCH(LARGE(Loans!$Y$2:$Y$1001,B31),Loans!$Y$2:$Y$1001,0))) | I31: =IF(C31="","",INDEX(Loans!$Q$2:$Q$1001,MATCH(LARGE(Loans!$Y$2:$Y$1001,B31),Loans!$Y$2:$Y$1001,0))) | J31: =IF(C31="","",INDEX(Loans!$C$2:$C$1001,MATCH(LARGE(Loans!$Y$2:$Y$1001,B31),Loans!$Y$2:$Y$1001,0))) | K31: =IF(C31="","",INDEX(Loans!$J$2:$J$1001,MATCH(LARGE(Loans!$Y$2:$Y$1001,B31),Loans!$Y$2:$Y$1001,0)))
B32: 2 | C32: =IF(LARGE(Loans!$Y$2:$Y$1001,B32)=0,"",INDEX(Loans!$A$2:$A$1001,MATCH(LARGE(Loans!$Y$2:$Y$1001,B32),Loans!$Y$2:$Y$1001,0))) | D32: =IF(C32="","",INDEX(Loans!$B$2:$B$1001,MATCH(LARGE(Loans!$Y$2:$Y$1001,B32),Loans!$Y$2:$Y$1001,0))) | E32: =IF(C32="","",INDEX(Loans!$E$2:$E$1001,MATCH(LARGE(Loans!$Y$2:$Y$1001,B32),Loans!$Y$2:$Y$1001,0))) | F32: =IF(C32="","",INDEX(Loans!$O$2:$O$1001,MATCH(LARGE(Loans!$Y$2:$Y$1001,B32),Loans!$Y$2:$Y$1001,0))) | H32: =IF(C32="","",INDEX(Loans!$K$2:$K$1001,MATCH(LARGE(Loans!$Y$2:$Y$1001,B32),Loans!$Y$2:$Y$1001,0))) | I32: =IF(C32="","",INDEX(Loans!$Q$2:$Q$1001,MATCH(LARGE(Loans!$Y$2:$Y$1001,B32),Loans!$Y$2:$Y$1001,0))) | J32: =IF(C32="","",INDEX(Loans!$C$2:$C$1001,MATCH(LARGE(Loans!$Y$2:$Y$1001,B32),Loans!$Y$2:$Y$1001,0))) | K32: =IF(C32="","",INDEX(Loans!$J$2:$J$1001,MATCH(LARGE(Loans!$Y$2:$Y$1001,B32),Loans!$Y$2:$Y$1001,0)))
B33: 3 | C33: =IF(LARGE(Loans!$Y$2:$Y$1001,B33)=0,"",INDEX(Loans!$A$2:$A$1001,MATCH(LARGE(Loans!$Y$2:$Y$1001,B33),Loans!$Y$2:$Y$1001,0))) | D33: =IF(C33="","",INDEX(Loans!$B$2:$B$1001,MATCH(LARGE(Loans!$Y$2:$Y$1001,B33),Loans!$Y$2:$Y$1001,0))) | E33: =IF(C33="","",INDEX(Loans!$E$2:$E$1001,MATCH(LARGE(Loans!$Y$2:$Y$1001,B33),Loans!$Y$2:$Y$1001,0))) | F33: =IF(C33="","",INDEX(Loans!$O$2:$O$1001,MATCH(LARGE(Loans!$Y$2:$Y$1001,B33),Loans!$Y$2:$Y$1001,0))) | H33: =IF(C33="","",INDEX(Loans!$K$2:$K$1001,MATCH(LARGE(Loans!$Y$2:$Y$1001,B33),Loans!$Y$2:$Y$1001,0))) | I33: =IF(C33="","",INDEX(Loans!$Q$2:$Q$1001,MATCH(LARGE(Loans!$Y$2:$Y$1001,B33),Loans!$Y$2:$Y$1001,0))) | J33: =IF(C33="","",INDEX(Loans!$C$2:$C$1001,MATCH(LARGE(Loans!$Y$2:$Y$1001,B33),Loans!$Y$2:$Y$1001,0))) | K33: =IF(C33="","",INDEX(Loans!$J$2:$J$1001,MATCH(LARGE(Loans!$Y$2:$Y$1001,B33),Loans!$Y$2:$Y$1001,0)))
B34: 4 | C34: =IF(LARGE(Loans!$Y$2:$Y$1001,B34)=0,"",INDEX(Loans!$A$2:$A$1001,MATCH(LARGE(Loans!$Y$2:$Y$1001,B34),Loans!$Y$2:$Y$1001,0))) | D34: =IF(C34="","",INDEX(Loans!$B$2:$B$1001,MATCH(LARGE(Loans!$Y$2:$Y$1001,B34),Loans!$Y$2:$Y$1001,0))) | E34: =IF(C34="","",INDEX(Loans!$E$2:$E$1001,MATCH(LARGE(Loans!$Y$2:$Y$1001,B34),Loans!$Y$2:$Y$1001,0))) | F34: =IF(C34="","",INDEX(Loans!$O$2:$O$1001,MATCH(LARGE(Loans!$Y$2:$Y$1001,B34),Loans!$Y$2:$Y$1001,0))) | H34: =IF(C34="","",INDEX(Loans!$K$2:$K$1001,MATCH(LARGE(Loans!$Y$2:$Y$1001,B34),Loans!$Y$2:$Y$1001,0))) | I34: =IF(C34="","",INDEX(Loans!$Q$2:$Q$1001,MATCH(LARGE(Loans!$Y$2:$Y$1001,B34),Loans!$Y$2:$Y$1001,0))) | J34: =IF(C34="","",INDEX(Loans!$C$2:$C$1001,MATCH(LARGE(Loans!$Y$2:$Y$1001,B34),Loans!$Y$2:$Y$1001,0))) | K34: =IF(C34="","",INDEX(Loans!$J$2:$J$1001,MATCH(LARGE(Loans!$Y$2:$Y$1001,B34),Loans!$Y$2:$Y$1001,0)))
B35: 5 | C35: =IF(LARGE(Loans!$Y$2:$Y$1001,B35)=0,"",INDEX(Loans!$A$2:$A$1001,MATCH(LARGE(Loans!$Y$2:$Y$1001,B35),Loans!$Y$2:$Y$1001,0))) | D35: =IF(C35="","",INDEX(Loans!$B$2:$B$1001,MATCH(LARGE(Loans!$Y$2:$Y$1001,B35),Loans!$Y$2:$Y$1001,0))) | E35: =IF(C35="","",INDEX(Loans!$E$2:$E$1001,MATCH(LARGE(Loans!$Y$2:$Y$1001,B35),Loans!$Y$2:$Y$1001,0))) | F35: =IF(C35="","",INDEX(Loans!$O$2:$O$1001,MATCH(LARGE(Loans!$Y$2:$Y$1001,B35),Loans!$Y$2:$Y$1001,0))) | H35: =IF(C35="","",INDEX(Loans!$K$2:$K$1001,MATCH(LARGE(Loans!$Y$2:$Y$1001,B35),Loans!$Y$2:$Y$1001,0))) | I35: =IF(C35="","",INDEX(Loans!$Q$2:$Q$1001,MATCH(LARGE(Loans!$Y$2:$Y$1001,B35),Loans!$Y$2:$Y$1001,0))) | J35: =IF(C35="","",INDEX(Loans!$C$2:$C$1001,MATCH(LARGE(Loans!$Y$2:$Y$1001,B35),Loans!$Y$2:$Y$1001,0))) | K35: =IF(C35="","",INDEX(Loans!$J$2:$J$1001,MATCH(LARGE(Loans!$Y$2:$Y$1001,B35),Loans!$Y$2:$Y$1001,0)))
B36: 6 | C36: =IF(LARGE(Loans!$Y$2:$Y$1001,B36)=0,"",INDEX(Loans!$A$2:$A$1001,MATCH(LARGE(Loans!$Y$2:$Y$1001,B36),Loans!$Y$2:$Y$1001,0))) | D36: =IF(C36="","",INDEX(Loans!$B$2:$B$1001,MATCH(LARGE(Loans!$Y$2:$Y$1001,B36),Loans!$Y$2:$Y$1001,0))) | E36: =IF(C36="","",INDEX(Loans!$E$2:$E$1001,MATCH(LARGE(Loans!$Y$2:$Y$1001,B36),Loans!$Y$2:$Y$1001,0))) | F36: =IF(C36="","",INDEX(Loans!$O$2:$O$1001,MATCH(LARGE(Loans!$Y$2:$Y$1001,B36),Loans!$Y$2:$Y$1001,0))) | H36: =IF(C36="","",INDEX(Loans!$K$2:$K$1001,MATCH(LARGE(Loans!$Y$2:$Y$1001,B36),Loans!$Y$2:$Y$1001,0))) | I36: =IF(C36="","",INDEX(Loans!$Q$2:$Q$1001,MATCH(LARGE(Loans!$Y$2:$Y$1001,B36),Loans!$Y$2:$Y$1001,0))) | J36: =IF(C36="","",INDEX(Loans!$C$2:$C$1001,MATCH(LARGE(Loans!$Y$2:$Y$1001,B36),Loans!$Y$2:$Y$1001,0))) | K36: =IF(C36="","",INDEX(Loans!$J$2:$J$1001,MATCH(LARGE(Loans!$Y$2:$Y$1001,B36),Loans!$Y$2:$Y$1001,0)))
B37: 7 | C37: =IF(LARGE(Loans!$Y$2:$Y$1001,B37)=0,"",INDEX(Loans!$A$2:$A$1001,MATCH(LARGE(Loans!$Y$2:$Y$1001,B37),Loans!$Y$2:$Y$1001,0))) | D37: =IF(C37="","",INDEX(Loans!$B$2:$B$1001,MATCH(LARGE(Loans!$Y$2:$Y$1001,B37),Loans!$Y$2:$Y$1001,0))) | E37: =IF(C37="","",INDEX(Loans!$E$2:$E$1001,MATCH(LARGE(Loans!$Y$2:$Y$1001,B37),Loans!$Y$2:$Y$1001,0))) | F37: =IF(C37="","",INDEX(Loans!$O$2:$O$1001,MATCH(LARGE(Loans!$Y$2:$Y$1001,B37),Loans!$Y$2:$Y$1001,0))) | H37: =IF(C37="","",INDEX(Loans!$K$2:$K$1001,MATCH(LARGE(Loans!$Y$2:$Y$1001,B37),Loans!$Y$2:$Y$1001,0))) | I37: =IF(C37="","",INDEX(Loans!$Q$2:$Q$1001,MATCH(LARGE(Loans!$Y$2:$Y$1001,B37),Loans!$Y$2:$Y$1001,0))) | J37: =IF(C37="","",INDEX(Loans!$C$2:$C$1001,MATCH(LARGE(Loans!$Y$2:$Y$1001,B37),Loans!$Y$2:$Y$1001,0))) | K37: =IF(C37="","",INDEX(Loans!$J$2:$J$1001,MATCH(LARGE(Loans!$Y$2:$Y$1001,B37),Loans!$Y$2:$Y$1001,0)))
B38: 8 | C38: =IF(LARGE(Loans!$Y$2:$Y$1001,B38)=0,"",INDEX(Loans!$A$2:$A$1001,MATCH(LARGE(Loans!$Y$2:$Y$1001,B38),Loans!$Y$2:$Y$1001,0))) | D38: =IF(C38="","",INDEX(Loans!$B$2:$B$1001,MATCH(LARGE(Loans!$Y$2:$Y$1001,B38),Loans!$Y$2:$Y$1001,0))) | E38: =IF(C38="","",INDEX(Loans!$E$2:$E$1001,MATCH(LARGE(Loans!$Y$2:$Y$1001,B38),Loans!$Y$2:$Y$1001,0))) | F38: =IF(C38="","",INDEX(Loans!$O$2:$O$1001,MATCH(LARGE(Loans!$Y$2:$Y$1001,B38),Loans!$Y$2:$Y$1001,0))) | H38: =IF(C38="","",INDEX(Loans!$K$2:$K$1001,MATCH(LARGE(Loans!$Y$2:$Y$1001,B38),Loans!$Y$2:$Y$1001,0))) | I38: =IF(C38="","",INDEX(Loans!$Q$2:$Q$1001,MATCH(LARGE(Loans!$Y$2:$Y$1001,B38),Loans!$Y$2:$Y$1001,0))) | J38: =IF(C38="","",INDEX(Loans!$C$2:$C$1001,MATCH(LARGE(Loans!$Y$2:$Y$1001,B38),Loans!$Y$2:$Y$1001,0))) | K38: =IF(C38="","",INDEX(Loans!$J$2:$J$1001,MATCH(LARGE(Loans!$Y$2:$Y$1001,B38),Loans!$Y$2:$Y$1001,0)))
B39: 9 | C39: =IF(LARGE(Loans!$Y$2:$Y$1001,B39)=0,"",INDEX(Loans!$A$2:$A$1001,MATCH(LARGE(Loans!$Y$2:$Y$1001,B39),Loans!$Y$2:$Y$1001,0))) | D39: =IF(C39="","",INDEX(Loans!$B$2:$B$1001,MATCH(LARGE(Loans!$Y$2:$Y$1001,B39),Loans!$Y$2:$Y$1001,0))) | E39: =IF(C39="","",INDEX(Loans!$E$2:$E$1001,MATCH(LARGE(Loans!$Y$2:$Y$1001,B39),Loans!$Y$2:$Y$1001,0))) | F39: =IF(C39="","",INDEX(Loans!$O$2:$O$1001,MATCH(LARGE(Loans!$Y$2:$Y$1001,B39),Loans!$Y$2:$Y$1001,0))) | H39: =IF(C39="","",INDEX(Loans!$K$2:$K$1001,MATCH(LARGE(Loans!$Y$2:$Y$1001,B39),Loans!$Y$2:$Y$1001,0))) | I39: =IF(C39="","",INDEX(Loans!$Q$2:$Q$1001,MATCH(LARGE(Loans!$Y$2:$Y$1001,B39),Loans!$Y$2:$Y$1001,0))) | J39: =IF(C39="","",INDEX(Loans!$C$2:$C$1001,MATCH(LARGE(Loans!$Y$2:$Y$1001,B39),Loans!$Y$2:$Y$1001,0))) | K39: =IF(C39="","",INDEX(Loans!$J$2:$J$1001,MATCH(LARGE(Loans!$Y$2:$Y$1001,B39),Loans!$Y$2:$Y$1001,0)))
B40: 10 | C40: =IF(LARGE(Loans!$Y$2:$Y$1001,B40)=0,"",INDEX(Loans!$A$2:$A$1001,MATCH(LARGE(Loans!$Y$2:$Y$1001,B40),Loans!$Y$2:$Y$1001,0))) | D40: =IF(C40="","",INDEX(Loans!$B$2:$B$1001,MATCH(LARGE(Loans!$Y$2:$Y$1001,B40),Loans!$Y$2:$Y$1001,0))) | E40: =IF(C40="","",INDEX(Loans!$E$2:$E$1001,MATCH(LARGE(Loans!$Y$2:$Y$1001,B40),Loans!$Y$2:$Y$1001,0))) | F40: =IF(C40="","",INDEX(Loans!$O$2:$O$1001,MATCH(LARGE(Loans!$Y$2:$Y$1001,B40),Loans!$Y$2:$Y$1001,0))) | H40: =IF(C40="","",INDEX(Loans!$K$2:$K$1001,MATCH(LARGE(Loans!$Y$2:$Y$1001,B40),Loans!$Y$2:$Y$1001,0))) | I40: =IF(C40="","",INDEX(Loans!$Q$2:$Q$1001,MATCH(LARGE(Loans!$Y$2:$Y$1001,B40),Loans!$Y$2:$Y$1001,0))) | J40: =IF(C40="","",INDEX(Loans!$C$2:$C$1001,MATCH(LARGE(Loans!$Y$2:$Y$1001,B40),Loans!$Y$2:$Y$1001,0))) | K40: =IF(C40="","",INDEX(Loans!$J$2:$J$1001,MATCH(LARGE(Loans!$Y$2:$Y$1001,B40),Loans!$Y$2:$Y$1001,0)))

Sheet Loans
A1: Loan ID | B1: Customer | C1: Branch | D1: Region | E1: Product | F1: Disbursal Date | G1: Loan Amount (₹) | H1: Rate (p.a.) | I1: Tenure (m) | J1: CIBIL | K1: DPD | L1: EMI (₹) | M1: Months Elapsed | N1: EMIs Paid | O1: Outstanding (₹) | P1: Overdue (₹) | Q1: DPD Bucket | R1: Asset Class | S1: NPA? | T1: Provision % | U1: Provision (₹) | V1: Risk Grade | W1: Vintage Qtr | X1: In Filter | Y1: NPA Rank Key
A2: LN100001 | B2: Ishaan Mohanty | C2: LKO-01 | D2: =INDEX(Branches!$C$2:$C$15,MATCH(C2,Branches!$A$2:$A$15,0)) | E2: Personal Loan | F2: 45610 | G2: 943000 | H2: 0.1471 | I2: 12 | J2: 735 | K2: 0 | L2: =ROUND(PMT(H2/12,I2,-G2),0) | M2: =MAX(0,(YEAR(AsOfDate)-YEAR(F2))*12+MONTH(AsOfDate)-MONTH(F2)) | N2: =MAX(0,MIN(I2,M2)-INT(K2/30)) | O2: =IF(N2>=I2,0,ROUND(PV(H2/12,I2-N2,-L2),0)) | P2: =MIN(I2,M2)*L2-N2*L2 | Q2: =INDEX(DPD_Bucket,MATCH(K2,DPD_From,1)) | R2: =INDEX(DPD_Class,MATCH(K2,DPD_From,1)) | S2: =INDEX(DPD_NPA,MATCH(K2,DPD_From,1)) | T2: =INDEX(DPD_Prov,MATCH(K2,DPD_From,1)) | U2: =ROUND(O2*T2,0) | V2: =INDEX(CIBIL_Grade,MATCH(J2,CIBIL_From,1)) | W2: =YEAR(F2)&"-Q"&ROUNDUP(MONTH(F2)/3,0) | X2: =IF(AND(OR(Dashboard!$C$4="All",D2=Dashboard!$C$4),OR(Dashboard!$C$5="All",E2=Dashboard!$C$5)),1,0) | Y2: =IF(AND(X2=1,S2="Yes"),O2+ROW()/1000000,0)
A3: LN100002 | B3: Ananya Sharma | C3: PAT-01 | D3: =INDEX(Branches!$C$2:$C$15,MATCH(C3,Branches!$A$2:$A$15,0)) | E3: Business Loan | F3: 45722 | G3: 4126000 | H3: 0.1789 | I3: 60 | J3: 765 | K3: 0 | L3: =ROUND(PMT(H3/12,I3,-G3),0) | M3: =MAX(0,(YEAR(AsOfDate)-YEAR(F3))*12+MONTH(AsOfDate)-MONTH(F3)) | N3: =MAX(0,MIN(I3,M3)-INT(K3/30)) | O3: =IF(N3>=I3,0,ROUND(PV(H3/12,I3-N3,-L3),0)) | P3: =MIN(I3,M3)*L3-N3*L3 | Q3: =INDEX(DPD_Bucket,MATCH(K3,DPD_From,1)) | R3: =INDEX(DPD_Class,MATCH(K3,DPD_From,1)) | S3: =INDEX(DPD_NPA,MATCH(K3,DPD_From,1)) | T3: =INDEX(DPD_Prov,MATCH(K3,DPD_From,1)) | U3: =ROUND(O3*T3,0) | V3: =INDEX(CIBIL_Grade,MATCH(J3,CIBIL_From,1)) | W3: =YEAR(F3)&"-Q"&ROUNDUP(MONTH(F3)/3,0) | X3: =IF(AND(OR(Dashboard!$C$4="All",D3=Dashboard!$C$4),OR(Dashboard!$C$5="All",E3=Dashboard!$C$5)),1,0) | Y3: =IF(AND(X3=1,S3="Yes"),O3+ROW()/1000000,0)
A4: LN100003 | B4: Arjun Menon | C4: GUW-01 | D4: =INDEX(Branches!$C$2:$C$15,MATCH(C4,Branches!$A$2:$A$15,0)) | E4: Auto Loan | F4: 45733 | G4: 950000 | H4: 0.0972 | I4: 48 | J4: 783 | K4: 0 | L4: =ROUND(PMT(H4/12,I4,-G4),0) | M4: =MAX(0,(YEAR(AsOfDate)-YEAR(F4))*12+MONTH(AsOfDate)-MONTH(F4)) | N4: =MAX(0,MIN(I4,M4)-INT(K4/30)) | O4: =IF(N4>=I4,0,ROUND(PV(H4/12,I4-N4,-L4),0)) | P4: =MIN(I4,M4)*L4-N4*L4 | Q4: =INDEX(DPD_Bucket,MATCH(K4,DPD_From,1)) | R4: =INDEX(DPD_Class,MATCH(K4,DPD_From,1)) | S4: =INDEX(DPD_NPA,MATCH(K4,DPD_From,1)) | T4: =INDEX(DPD_Prov,MATCH(K4,DPD_From,1)) | U4: =ROUND(O4*T4,0) | V4: =INDEX(CIBIL_Grade,MATCH(J4,CIBIL_From,1)) | W4: =YEAR(F4)&"-Q"&ROUNDUP(MONTH(F4)/3,0) | X4: =IF(AND(OR(Dashboard!$C$4="All",D4=Dashboard!$C$4),OR(Dashboard!$C$5="All",E4=Dashboard!$C$5)),1,0) | Y4: =IF(AND(X4=1,S4="Yes"),O4+ROW()/1000000,0)
A5: LN100004 | B5: Kavya Iyer | C5: LKO-01 | D5: =INDEX(Branches!$C$2:$C$15,MATCH(C5,Branches!$A$2:$A$15,0)) | E5: Home Loan | F5: 45918 | G5: 5811000 | H5: 0.0928 | I5: 180 | J5: 721 | K5: 0 | L5: =ROUND(PMT(H5/12,I5,-G5),0) | M5: =MAX(0,(YEAR(AsOfDate)-YEAR(F5))*12+MONTH(AsOfDate)-MONTH(F5)) | N5: =MAX(0,MIN(I5,M5)-INT(K5/30)) | O5: =IF(N5>=I5,0,ROUND(PV(H5/12,I5-N5,-L5),0)) | P5: =MIN(I5,M5)*L5-N5*L5 | Q5: =INDEX(DPD_Bucket,MATCH(K5,DPD_From,1)) | R5: =INDEX(DPD_Class,MATCH(K5,DPD_From,1)) | S5: =INDEX(DPD_NPA,MATCH(K5,DPD_From,1)) | T5: =INDEX(DPD_Prov,MATCH(K5,DPD_From,1)) | U5: =ROUND(O5*T5,0) | V5: =INDEX(CIBIL_Grade,MATCH(J5,CIBIL_From,1)) | W5: =YEAR(F5)&"-Q"&ROUNDUP(MONTH(F5)/3,0) | X5: =IF(AND(OR(Dashboard!$C$4="All",D5=Dashboard!$C$4),OR(Dashboard!$C$5="All",E5=Dashboard!$C$5)),1,0) | Y5: =IF(AND(X5=1,S5="Yes"),O5+ROW()/1000000,0)
A6: LN100005 | B6: Diya Iyer | C6: GUW-01 | D6: =INDEX(Branches!$C$2:$C$15,MATCH(C6,Branches!$A$2:$A$15,0)) | E6: Gold Loan | F6: 45780 | G6: 155000 | H6: 0.093 | I6: 12 | J6: 730 | K6: 0 | L6: =ROUND(PMT(H6/12,I6,-G6),0) | M6: =MAX(0,(YEAR(AsOfDate)-YEAR(F6))*12+MONTH(AsOfDate)-MONTH(F6)) | N6: =MAX(0,MIN(I6,M6)-INT(K6/30)) | O6: =IF(N6>=I6,0,ROUND(PV(H6/12,I6-N6,-L6),0)) | P6: =MIN(I6,M6)*L6-N6*L6 | Q6: =INDEX(DPD_Bucket,MATCH(K6,DPD_From,1)) | R6: =INDEX(DPD_Class,MATCH(K6,DPD_From,1)) | S6: =INDEX(DPD_NPA,MATCH(K6,DPD_From,1)) | T6: =INDEX(DPD_Prov,MATCH(K6,DPD_From,1)) | U6: =ROUND(O6*T6,0) | V6: =INDEX(CIBIL_Grade,MATCH(J6,CIBIL_From,1)) | W6: =YEAR(F6)&"-Q"&ROUNDUP(MONTH(F6)/3,0) | X6: =IF(AND(OR(Dashboard!$C$4="All",D6=Dashboard!$C$4),OR(Dashboard!$C$5="All",E6=Dashboard!$C$5)),1,0) | Y6: =IF(AND(X6=1,S6="Yes"),O6+ROW()/1000000,0)
A7: LN100006 | B7: Ishaan Gupta | C7: BBS-01 | D7: =INDEX(Branches!$C$2:$C$15,MATCH(C7,Branches!$A$2:$A$15,0)) | E7: Auto Loan | F7: 45840 | G7: 1899000 | H7: 0.1091 | I7: 60 | J7: 718 | K7: 0 | L7: =ROUND(PMT(H7/12,I7,-G7),0) | M7: =MAX(0,(YEAR(AsOfDate)-YEAR(F7))*12+MONTH(AsOfDate)-MONTH(F7)) | N7: =MAX(0,MIN(I7,M7)-INT(K7/30)) | O7: =IF(N7>=I7,0,ROUND(PV(H7/12,I7-N7,-L7),0)) | P7: =MIN(I7,M7)*L7-N7*L7 | Q7: =INDEX(DPD_Bucket,MATCH(K7,DPD_From,1)) | R7: =INDEX(DPD_Class,MATCH(K7,DPD_From,1)) | S7: =INDEX(DPD_NPA,MATCH(K7,DPD_From,1)) | T7: =INDEX(DPD_Prov,MATCH(K7,DPD_From,1)) | U7: =ROUND(O7*T7,0) | V7: =INDEX(CIBIL_Grade,MATCH(J7,CIBIL_From,1)) | W7: =YEAR(F7)&"-Q"&ROUNDUP(MONTH(F7)/3,0) | X7: =IF(AND(OR(Dashboard!$C$4="All",D7=Dashboard!$C$4),OR(Dashboard!$C$5="All",E7=Dashboard!$C$5)),1,0) | Y7: =IF(AND(X7=1,S7="Yes"),O7+ROW()/1000000,0)
A8: LN100007 | B8: Lakshmi Kulkarni | C8: KOC-01 | D8: =INDEX(Branches!$C$2:$C$15,MATCH(C8,Branches!$A$2:$A$15,0)) | E8: Personal Loan | F8: 45672 | G8: 1058000 | H8: 0.1682 | I8: 24 | J8: 762 | K8: 0 | L8: =ROUND(PMT(H8/12,I8,-G8),0) | M8: =MAX(0,(YEAR(AsOfDate)-YEAR(F8))*12+MONTH(AsOfDate)-MONTH(F8)) | N8: =MAX(0,MIN(I8,M8)-INT(K8/30)) | O8: =IF(N8>=I8,0,ROUND(PV(H8/12,I8-N8,-L8),0)) | P8: =MIN(I8,M8)*L8-N8*L8 | Q8: =INDEX(DPD_Bucket,MATCH(K8,DPD_From,1)) | R8: =INDEX(DPD_Class,MATCH(K8,DPD_From,1)) | S8: =INDEX(DPD_NPA,MATCH(K8,DPD_From,1)) | T8: =INDEX(DPD_Prov,MATCH(K8,DPD_From,1)) | U8: =ROUND(O8*T8,0) | V8: =INDEX(CIBIL_Grade,MATCH(J8,CIBIL_From,1)) | W8: =YEAR(F8)&"-Q"&ROUNDUP(MONTH(F8)/3,0) | X8: =IF(AND(OR(Dashboard!$C$4="All",D8=Dashboard!$C$4),OR(Dashboard!$C$5="All",E8=Dashboard!$C$5)),1,0) | Y8: =IF(AND(X8=1,S8="Yes"),O8+ROW()/1000000,0)
A9: LN100008 | B9: Kavya Gupta | C9: CHN-01 | D9: =INDEX(Branches!$C$2:$C$15,MATCH(C9,Branches!$A$2:$A$15,0)) | E9: Business Loan | F9: 46108 | G9: 1449000 | H9: 0.196 | I9: 24 | J9: 780 | K9: 0 | L9: =ROUND(PMT(H9/12,I9,-G9),0) | M9: =MAX(0,(YEAR(AsOfDate)-YEAR(F9))*12+MONTH(AsOfDate)-MONTH(F9)) | N9: =MAX(0,MIN(I9,M9)-INT(K9/30)) | O9: =IF(N9>=I9,0,ROUND(PV(H9/12,I9-N9,-L9),0)) | P9: =MIN(I9,M9)*L9-N9*L9 | Q9: =INDEX(DPD_Bucket,MATCH(K9,DPD_From,1)) | R9: =INDEX(DPD_Class,MATCH(K9,DPD_From,1)) | S9: =INDEX(DPD_NPA,MATCH(K9,DPD_From,1)) | T9: =INDEX(DPD_Prov,MATCH(K9,DPD_From,1)) | U9: =ROUND(O9*T9,0) | V9: =INDEX(CIBIL_Grade,MATCH(J9,CIBIL_From,1)) | W9: =YEAR(F9)&"-Q"&ROUNDUP(MONTH(F9)/3,0) | X9: =IF(AND(OR(Dashboard!$C$4="All",D9=Dashboard!$C$4),OR(Dashboard!$C$5="All",E9=Dashboard!$C$5)),1,0) | Y9: =IF(AND(X9=1,S9="Yes"),O9+ROW()/1000000,0)
A10: LN100009 | B10: Riya Reddy | C10: MUM-01 | D10: =INDEX(Branches!$C$2:$C$15,MATCH(C10,Branches!$A$2:$A$15,0)) | E10: Business Loan | F10: 45738 | G10: 1128000 | H10: 0.1821 | I10: 36 | J10: 704 | K10: 0 | L10: =ROUND(PMT(H10/12,I10,-G10),0) | M10: =MAX(0,(YEAR(AsOfDate)-YEAR(F10))*12+MONTH(AsOfDate)-MONTH(F10)) | N10: =MAX(0,MIN(I10,M10)-INT(K10/30)) | O10: =IF(N10>=I10,0,ROUND(PV(H10/12,I10-N10,-L10),0)) | P10: =MIN(I10,M10)*L10-N10*L10 | Q10: =INDEX(DPD_Bucket,MATCH(K10,DPD_From,1)) | R10: =INDEX(DPD_Class,MATCH(K10,DPD_From,1)) | S10: =INDEX(DPD_NPA,MATCH(K10,DPD_From,1)) | T10: =INDEX(DPD_Prov,MATCH(K10,DPD_From,1)) | U10: =ROUND(O10*T10,0) | V10: =INDEX(CIBIL_Grade,MATCH(J10,CIBIL_From,1)) | W10: =YEAR(F10)&"-Q"&ROUNDUP(MONTH(F10)/3,0) | X10: =IF(AND(OR(Dashboard!$C$4="All",D10=Dashboard!$C$4),OR(Dashboard!$C$5="All",E10=Dashboard!$C$5)),1,0) | Y10: =IF(AND(X10=1,S10="Yes"),O10+ROW()/1000000,0)
A11: LN100010 | B11: Kavya Menon | C11: KOC-01 | D11: =INDEX(Branches!$C$2:$C$15,MATCH(C11,Branches!$A$2:$A$15,0)) | E11: Personal Loan | F11: 45296 | G11: 1496000 | H11: 0.1154 | I11: 60 | J11: 689 | K11: 0 | L11: =ROUND(PMT(H11/12,I11,-G11),0) | M11: =MAX(0,(YEAR(AsOfDate)-YEAR(F11))*12+MONTH(AsOfDate)-MONTH(F11)) | N11: =MAX(0,MIN(I11,M11)-INT(K11/30)) | O11: =IF(N11>=I11,0,ROUND(PV(H11/12,I11-N11,-L11),0)) | P11: =MIN(I11,M11)*L11-N11*L11 | Q11: =INDEX(DPD_Bucket,MATCH(K11,DPD_From,1)) | R11: =INDEX(DPD_Class,MATCH(K11,DPD_From,1)) | S11: =INDEX(DPD_NPA,MATCH(K11,DPD_From,1)) | T11: =INDEX(DPD_Prov,MATCH(K11,DPD_From,1)) | U11: =ROUND(O11*T11,0) | V11: =INDEX(CIBIL_Grade,MATCH(J11,CIBIL_From,1)) | W11: =YEAR(F11)&"-Q"&ROUNDUP(MONTH(F11)/3,0) | X11: =IF(AND(OR(Dashboard!$C$4="All",D11=Dashboard!$C$4),OR(Dashboard!$C$5="All",E11=Dashboard!$C$5)),1,0) | Y11: =IF(AND(X11=1,S11="Yes"),O11+ROW()/1000000,0)
A12: LN100011 | B12: Suresh Iyer | C12: AMD-01 | D12: =INDEX(Branches!$C$2:$C$15,MATCH(C12,Branches!$A$2:$A$15,0)) | E12: Personal Loan | F12: 45949 | G12: 634000 | H12: 0.1797 | I12: 12 | J12: 753 | K12: 0 | L12: =ROUND(PMT(H12/12,I12,-G12),0) | M12: =MAX(0,(YEAR(AsOfDate)-YEAR(F12))*12+MONTH(AsOfDate)-MONTH(F12)) | N12: =MAX(0,MIN(I12,M12)-INT(K12/30)) | O12: =IF(N12>=I12,0,ROUND(PV(H12/12,I12-N12,-L12),0)) | P12: =MIN(I12,M12)*L12-N12*L12 | Q12: =INDEX(DPD_Bucket,MATCH(K12,DPD_From,1)) | R12: =INDEX(DPD_Class,MATCH(K12,DPD_From,1)) | S12: =INDEX(DPD_NPA,MATCH(K12,DPD_From,1)) | T12: =INDEX(DPD_Prov,MATCH(K12,DPD_From,1)) | U12: =ROUND(O12*T12,0) | V12: =INDEX(CIBIL_Grade,MATCH(J12,CIBIL_From,1)) | W12: =YEAR(F12)&"-Q"&ROUNDUP(MONTH(F12)/3,0) | X12: =IF(AND(OR(Dashboard!$C$4="All",D12=Dashboard!$C$4),OR(Dashboard!$C$5="All",E12=Dashboard!$C$5)),1,0) | Y12: =IF(AND(X12=1,S12="Yes"),O12+ROW()/1000000,0)
A13: LN100012 | B13: Arjun Kulkarni | C13: PAT-01 | D13: =INDEX(Branches!$C$2:$C$15,MATCH(C13,Branches!$A$2:$A$15,0)) | E13: Personal Loan | F13: 46150 | G13: 474000 | H13: 0.1531 | I13: 60 | J13: 761 | K13: 0 | L13: =ROUND(PMT(H13/12,I13,-G13),0) | M13: =MAX(0,(YEAR(AsOfDate)-YEAR(F13))*12+MONTH(AsOfDate)-MONTH(F13)) | N13: =MAX(0,MIN(I13,M13)-INT(K13/30)) | O13: =IF(N13>=I13,0,ROUND(PV(H13/12,I13-N13,-L13),0)) | P13: =MIN(I13,M13)*L13-N13*L13 | Q13: =INDEX(DPD_Bucket,MATCH(K13,DPD_From,1)) | R13: =INDEX(DPD_Class,MATCH(K13,DPD_From,1)) | S13: =INDEX(DPD_NPA,MATCH(K13,DPD_From,1)) | T13: =INDEX(DPD_Prov,MATCH(K13,DPD_From,1)) | U13: =ROUND(O13*T13,0) | V13: =INDEX(CIBIL_Grade,MATCH(J13,CIBIL_From,1)) | W13: =YEAR(F13)&"-Q"&ROUNDUP(MONTH(F13)/3,0) | X13: =IF(AND(OR(Dashboard!$C$4="All",D13=Dashboard!$C$4),OR(Dashboard!$C$5="All",E13=Dashboard!$C$5)),1,0) | Y13: =IF(AND(X13=1,S13="Yes"),O13+ROW()/1000000,0)
... A1001: LN101000 | B1001: Ananya Rao | C1001: JAI-01 | D1001: =INDEX(Branches!$C$2:$C$15,MATCH(C1001,Branches!$A$2:$A$15,0)) | E1001: Personal Loan | F1001: 45306 | G1001: 251000 | H1001: 0.1337 | I1001: 48 | J1001: 728 | K1001: 0 | L1001: =ROUND(PMT(H1001/12,I1001,-G1001),0) | M1001: =MAX(0,(YEAR(AsOfDate)-YEAR(F1001))*12+MONTH(AsOfDate)-MONTH(F1001)) | N1001: =MAX(0,MIN(I1001,M1001)-INT(K1001/30)) | O1001: =IF(N1001>=I1001,0,ROUND(PV(H1001/12,I1001-N1001,-L1001),0)) | P1001: =MIN(I1001,M1001)*L1001-N1001*L1001 | Q1001: =INDEX(DPD_Bucket,MATCH(K1001,DPD_From,1)) | R1001: =INDEX(DPD_Class,MATCH(K1001,DPD_From,1)) | S1001: =INDEX(DPD_NPA,MATCH(K1001,DPD_From,1)) | T1001: =INDEX(DPD_Prov,MATCH(K1001,DPD_From,1)) | U1001: =ROUND(O1001*T1001,0) | V1001: =INDEX(CIBIL_Grade,MATCH(J1001,CIBIL_From,1)) | W1001: =YEAR(F1001)&"-Q"&ROUNDUP(MONTH(F1001)/3,0) | X1001: =IF(AND(OR(Dashboard!$C$4="All",D1001=Dashboard!$C$4),OR(Dashboard!$C$5="All",E1001=Dashboard!$C$5)),1,0) | Y1001: =IF(AND(X1001=1,S1001="Yes"),O1001+ROW()/1000000,0)

Sheet Vintage
B2: Vintage (Cohort) Analysis
B3: How each disbursal quarter is performing today — later-dated bad cohorts signal underwriting drift.
B5: Vintage | C5: Loans | D5: Disbursed (₹ Cr) | E5: Outstanding (₹ Cr) | F5: GNPA (₹ Cr) | G5: GNPA % | H5: Avg CIBIL
B6: 2023-Q3 | C6: =COUNTIFS(Loans!$W$2:$W$1001,B6) | D6: =SUMIFS(Loans!$G$2:$G$1001,Loans!$W$2:$W$1001,B6)/10^7 | E6: =SUMIFS(Loans!$O$2:$O$1001,Loans!$W$2:$W$1001,B6)/10^7 | F6: =SUMIFS(Loans!$O$2:$O$1001,Loans!$W$2:$W$1001,B6,Loans!$S$2:$S$1001,"Yes")/10^7 | G6: =IFERROR(F6/E6,0) | H6: =IFERROR(AVERAGEIFS(Loans!$J$2:$J$1001,Loans!$W$2:$W$1001,B6),0)
B7: 2023-Q4 | C7: =COUNTIFS(Loans!$W$2:$W$1001,B7) | D7: =SUMIFS(Loans!$G$2:$G$1001,Loans!$W$2:$W$1001,B7)/10^7 | E7: =SUMIFS(Loans!$O$2:$O$1001,Loans!$W$2:$W$1001,B7)/10^7 | F7: =SUMIFS(Loans!$O$2:$O$1001,Loans!$W$2:$W$1001,B7,Loans!$S$2:$S$1001,"Yes")/10^7 | G7: =IFERROR(F7/E7,0) | H7: =IFERROR(AVERAGEIFS(Loans!$J$2:$J$1001,Loans!$W$2:$W$1001,B7),0)
B8: 2024-Q1 | C8: =COUNTIFS(Loans!$W$2:$W$1001,B8) | D8: =SUMIFS(Loans!$G$2:$G$1001,Loans!$W$2:$W$1001,B8)/10^7 | E8: =SUMIFS(Loans!$O$2:$O$1001,Loans!$W$2:$W$1001,B8)/10^7 | F8: =SUMIFS(Loans!$O$2:$O$1001,Loans!$W$2:$W$1001,B8,Loans!$S$2:$S$1001,"Yes")/10^7 | G8: =IFERROR(F8/E8,0) | H8: =IFERROR(AVERAGEIFS(Loans!$J$2:$J$1001,Loans!$W$2:$W$1001,B8),0)
B9: 2024-Q2 | C9: =COUNTIFS(Loans!$W$2:$W$1001,B9) | D9: =SUMIFS(Loans!$G$2:$G$1001,Loans!$W$2:$W$1001,B9)/10^7 | E9: =SUMIFS(Loans!$O$2:$O$1001,Loans!$W$2:$W$1001,B9)/10^7 | F9: =SUMIFS(Loans!$O$2:$O$1001,Loans!$W$2:$W$1001,B9,Loans!$S$2:$S$1001,"Yes")/10^7 | G9: =IFERROR(F9/E9,0) | H9: =IFERROR(AVERAGEIFS(Loans!$J$2:$J$1001,Loans!$W$2:$W$1001,B9),0)
B10: 2024-Q3 | C10: =COUNTIFS(Loans!$W$2:$W$1001,B10) | D10: =SUMIFS(Loans!$G$2:$G$1001,Loans!$W$2:$W$1001,B10)/10^7 | E10: =SUMIFS(Loans!$O$2:$O$1001,Loans!$W$2:$W$1001,B10)/10^7 | F10: =SUMIFS(Loans!$O$2:$O$1001,Loans!$W$2:$W$1001,B10,Loans!$S$2:$S$1001,"Yes")/10^7 | G10: =IFERROR(F10/E10,0) | H10: =IFERROR(AVERAGEIFS(Loans!$J$2:$J$1001,Loans!$W$2:$W$1001,B10),0)
B11: 2024-Q4 | C11: =COUNTIFS(Loans!$W$2:$W$1001,B11) | D11: =SUMIFS(Loans!$G$2:$G$1001,Loans!$W$2:$W$1001,B11)/10^7 | E11: =SUMIFS(Loans!$O$2:$O$1001,Loans!$W$2:$W$1001,B11)/10^7 | F11: =SUMIFS(Loans!$O$2:$O$1001,Loans!$W$2:$W$1001,B11,Loans!$S$2:$S$1001,"Yes")/10^7 | G11: =IFERROR(F11/E11,0) | H11: =IFERROR(AVERAGEIFS(Loans!$J$2:$J$1001,Loans!$W$2:$W$1001,B11),0)
B12: 2025-Q1 | C12: =COUNTIFS(Loans!$W$2:$W$1001,B12) | D12: =SUMIFS(Loans!$G$2:$G$1001,Loans!$W$2:$W$1001,B12)/10^7 | E12: =SUMIFS(Loans!$O$2:$O$1001,Loans!$W$2:$W$1001,B12)/10^7 | F12: =SUMIFS(Loans!$O$2:$O$1001,Loans!$W$2:$W$1001,B12,Loans!$S$2:$S$1001,"Yes")/10^7 | G12: =IFERROR(F12/E12,0) | H12: =IFERROR(AVERAGEIFS(Loans!$J$2:$J$1001,Loans!$W$2:$W$1001,B12),0)
B13: 2025-Q2 | C13: =COUNTIFS(Loans!$W$2:$W$1001,B13) | D13: =SUMIFS(Loans!$G$2:$G$1001,Loans!$W$2:$W$1001,B13)/10^7 | E13: =SUMIFS(Loans!$O$2:$O$1001,Loans!$W$2:$W$1001,B13)/10^7 | F13: =SUMIFS(Loans!$O$2:$O$1001,Loans!$W$2:$W$1001,B13,Loans!$S$2:$S$1001,"Yes")/10^7 | G13: =IFERROR(F13/E13,0) | H13: =IFERROR(AVERAGEIFS(Loans!$J$2:$J$1001,Loans!$W$2:$W$1001,B13),0)
B14: 2025-Q3 | C14: =COUNTIFS(Loans!$W$2:$W$1001,B14) | D14: =SUMIFS(Loans!$G$2:$G$1001,Loans!$W$2:$W$1001,B14)/10^7 | E14: =SUMIFS(Loans!$O$2:$O$1001,Loans!$W$2:$W$1001,B14)/10^7 | F14: =SUMIFS(Loans!$O$2:$O$1001,Loans!$W$2:$W$1001,B14,Loans!$S$2:$S$1001,"Yes")/10^7 | G14: =IFERROR(F14/E14,0) | H14: =IFERROR(AVERAGEIFS(Loans!$J$2:$J$1001,Loans!$W$2:$W$1001,B14),0)
B15: 2025-Q4 | C15: =COUNTIFS(Loans!$W$2:$W$1001,B15) | D15: =SUMIFS(Loans!$G$2:$G$1001,Loans!$W$2:$W$1001,B15)/10^7 | E15: =SUMIFS(Loans!$O$2:$O$1001,Loans!$W$2:$W$1001,B15)/10^7 | F15: =SUMIFS(Loans!$O$2:$O$1001,Loans!$W$2:$W$1001,B15,Loans!$S$2:$S$1001,"Yes")/10^7 | G15: =IFERROR(F15/E15,0) | H15: =IFERROR(AVERAGEIFS(Loans!$J$2:$J$1001,Loans!$W$2:$W$1001,B15),0)
B16: 2026-Q1 | C16: =COUNTIFS(Loans!$W$2:$W$1001,B16) | D16: =SUMIFS(Loans!$G$2:$G$1001,Loans!$W$2:$W$1001,B16)/10^7 | E16: =SUMIFS(Loans!$O$2:$O$1001,Loans!$W$2:$W$1001,B16)/10^7 | F16: =SUMIFS(Loans!$O$2:$O$1001,Loans!$W$2:$W$1001,B16,Loans!$S$2:$S$1001,"Yes")/10^7 | G16: =IFERROR(F16/E16,0) | H16: =IFERROR(AVERAGEIFS(Loans!$J$2:$J$1001,Loans!$W$2:$W$1001,B16),0)
B17: 2026-Q2 | C17: =COUNTIFS(Loans!$W$2:$W$1001,B17) | D17: =SUMIFS(Loans!$G$2:$G$1001,Loans!$W$2:$W$1001,B17)/10^7 | E17: =SUMIFS(Loans!$O$2:$O$1001,Loans!$W$2:$W$1001,B17)/10^7 | F17: =SUMIFS(Loans!$O$2:$O$1001,Loans!$W$2:$W$1001,B17,Loans!$S$2:$S$1001,"Yes")/10^7 | G17: =IFERROR(F17/E17,0) | H17: =IFERROR(AVERAGEIFS(Loans!$J$2:$J$1001,Loans!$W$2:$W$1001,B17),0)
B18: Total | C18: =SUM(C6:C17) | D18: =SUM(D6:D17) | E18: =SUM(E6:E17) | F18: =SUM(F6:F17) | G18: =IFERROR(F18/E18,0)

Sheet EMI Calculator
B2: EMI Calculator & Amortization
E3: # | F3: Date | G3: Opening (₹) | H3: EMI (₹) | I3: Interest (₹) | J3: Principal (₹) | K3: Closing (₹)
B4: Loan Amount (₹) | C4: 2500000 | E4: =IF(1>$C$6,"",1) | F4: =IF(E4="","",EDATE($C$7,E4-1)) | G4: =IF(E4="","",$C$4) | H4: =IF(E4="","",$C$9) | I4: =IF(E4="","",-IPMT($C$5/12,E4,$C$6,$C$4)) | J4: =IF(E4="","",-PPMT($C$5/12,E4,$C$6,$C$4)) | K4: =IF(E4="","",MAX(0,G4-J4))
B5: Interest Rate (p.a.) | C5: 0.0875 | E5: =IF(2>$C$6,"",2) | F5: =IF(E5="","",EDATE($C$7,E5-1)) | G5: =IF(E5="","",K4) | H5: =IF(E5="","",$C$9) | I5: =IF(E5="","",-IPMT($C$5/12,E5,$C$6,$C$4)) | J5: =IF(E5="","",-PPMT($C$5/12,E5,$C$6,$C$4)) | K5: =IF(E5="","",MAX(0,G5-J5))
B6: Tenure (months) | C6: 120 | E6: =IF(3>$C$6,"",3) | F6: =IF(E6="","",EDATE($C$7,E6-1)) | G6: =IF(E6="","",K5) | H6: =IF(E6="","",$C$9) | I6: =IF(E6="","",-IPMT($C$5/12,E6,$C$6,$C$4)) | J6: =IF(E6="","",-PPMT($C$5/12,E6,$C$6,$C$4)) | K6: =IF(E6="","",MAX(0,G6-J6))
B7: First EMI Date | C7: 46208 | E7: =IF(4>$C$6,"",4) | F7: =IF(E7="","",EDATE($C$7,E7-1)) | G7: =IF(E7="","",K6) | H7: =IF(E7="","",$C$9) | I7: =IF(E7="","",-IPMT($C$5/12,E7,$C$6,$C$4)) | J7: =IF(E7="","",-PPMT($C$5/12,E7,$C$6,$C$4)) | K7: =IF(E7="","",MAX(0,G7-J7))
E8: =IF(5>$C$6,"",5) | F8: =IF(E8="","",EDATE($C$7,E8-1)) | G8: =IF(E8="","",K7) | H8: =IF(E8="","",$C$9) | I8: =IF(E8="","",-IPMT($C$5/12,E8,$C$6,$C$4)) | J8: =IF(E8="","",-PPMT($C$5/12,E8,$C$6,$C$4)) | K8: =IF(E8="","",MAX(0,G8-J8))
B9: Monthly EMI (₹) | C9: =IFERROR(PMT(C5/12,C6,-C4),0) | E9: =IF(6>$C$6,"",6) | F9: =IF(E9="","",EDATE($C$7,E9-1)) | G9: =IF(E9="","",K8) | H9: =IF(E9="","",$C$9) | I9: =IF(E9="","",-IPMT($C$5/12,E9,$C$6,$C$4)) | J9: =IF(E9="","",-PPMT($C$5/12,E9,$C$6,$C$4)) | K9: =IF(E9="","",MAX(0,G9-J9))
B10: Total Interest (₹) | C10: =C9*C6-C4 | E10: =IF(7>$C$6,"",7) | F10: =IF(E10="","",EDATE($C$7,E10-1)) | G10: =IF(E10="","",K9) | H10: =IF(E10="","",$C$9) | I10: =IF(E10="","",-IPMT($C$5/12,E10,$C$6,$C$4)) | J10: =IF(E10="","",-PPMT($C$5/12,E10,$C$6,$C$4)) | K10: =IF(E10="","",MAX(0,G10-J10))
B11: Total Payable (₹) | C11: =C9*C6 | E11: =IF(8>$C$6,"",8) | F11: =IF(E11="","",EDATE($C$7,E11-1)) | G11: =IF(E11="","",K10) | H11: =IF(E11="","",$C$9) | I11: =IF(E11="","",-IPMT($C$5/12,E11,$C$6,$C$4)) | J11: =IF(E11="","",-PPMT($C$5/12,E11,$C$6,$C$4)) | K11: =IF(E11="","",MAX(0,G11-J11))
B12: Interest / Principal | C12: =IFERROR(C10/C4,0) | E12: =IF(9>$C$6,"",9) | F12: =IF(E12="","",EDATE($C$7,E12-1)) | G12: =IF(E12="","",K11) | H12: =IF(E12="","",$C$9) | I12: =IF(E12="","",-IPMT($C$5/12,E12,$C$6,$C$4)) | J12: =IF(E12="","",-PPMT($C$5/12,E12,$C$6,$C$4)) | K12: =IF(E12="","",MAX(0,G12-J12))
B13: Last EMI Date | C13: =EDATE(C7,C6-1) | E13: =IF(10>$C$6,"",10) | F13: =IF(E13="","",EDATE($C$7,E13-1)) | G13: =IF(E13="","",K12) | H13: =IF(E13="","",$C$9) | I13: =IF(E13="","",-IPMT($C$5/12,E13,$C$6,$C$4)) | J13: =IF(E13="","",-PPMT($C$5/12,E13,$C$6,$C$4)) | K13: =IF(E13="","",MAX(0,G13-J13))
E14: =IF(11>$C$6,"",11) | F14: =IF(E14="","",EDATE($C$7,E14-1)) | G14: =IF(E14="","",K13) | H14: =IF(E14="","",$C$9) | I14: =IF(E14="","",-IPMT($C$5/12,E14,$C$6,$C$4)) | J14: =IF(E14="","",-PPMT($C$5/12,E14,$C$6,$C$4)) | K14: =IF(E14="","",MAX(0,G14-J14))
B15: Schedule shows up to 360 months; rows beyond tenure stay blank. | E15: =IF(12>$C$6,"",12) | F15: =IF(E15="","",EDATE($C$7,E15-1)) | G15: =IF(E15="","",K14) | H15: =IF(E15="","",$C$9) | I15: =IF(E15="","",-IPMT($C$5/12,E15,$C$6,$C$4)) | J15: =IF(E15="","",-PPMT($C$5/12,E15,$C$6,$C$4)) | K15: =IF(E15="","",MAX(0,G15-J15))
E16: =IF(13>$C$6,"",13) | F16: =IF(E16="","",EDATE($C$7,E16-1)) | G16: =IF(E16="","",K15) | H16: =IF(E16="","",$C$9) | I16: =IF(E16="","",-IPMT($C$5/12,E16,$C$6,$C$4)) | J16: =IF(E16="","",-PPMT($C$5/12,E16,$C$6,$C$4)) | K16: =IF(E16="","",MAX(0,G16-J16))
E17: =IF(14>$C$6,"",14) | F17: =IF(E17="","",EDATE($C$7,E17-1)) | G17: =IF(E17="","",K16) | H17: =IF(E17="","",$C$9) | I17: =IF(E17="","",-IPMT($C$5/12,E17,$C$6,$C$4)) | J17: =IF(E17="","",-PPMT($C$5/12,E17,$C$6,$C$4)) | K17: =IF(E17="","",MAX(0,G17-J17))
E18: =IF(15>$C$6,"",15) | F18: =IF(E18="","",EDATE($C$7,E18-1)) | G18: =IF(E18="","",K17) | H18: =IF(E18="","",$C$9) | I18: =IF(E18="","",-IPMT($C$5/12,E18,$C$6,$C$4)) | J18: =IF(E18="","",-PPMT($C$5/12,E18,$C$6,$C$4)) | K18: =IF(E18="","",MAX(0,G18-J18))
E19: =IF(16>$C$6,"",16) | F19: =IF(E19="","",EDATE($C$7,E19-1)) | G19: =IF(E19="","",K18) | H19: =IF(E19="","",$C$9) | I19: =IF(E19="","",-IPMT($C$5/12,E19,$C$6,$C$4)) | J19: =IF(E19="","",-PPMT($C$5/12,E19,$C$6,$C$4)) | K19: =IF(E19="","",MAX(0,G19-J19))
E20: =IF(17>$C$6,"",17) | F20: =IF(E20="","",EDATE($C$7,E20-1)) | G20: =IF(E20="","",K19) | H20: =IF(E20="","",$C$9) | I20: =IF(E20="","",-IPMT($C$5/12,E20,$C$6,$C$4)) | J20: =IF(E20="","",-PPMT($C$5/12,E20,$C$6,$C$4)) | K20: =IF(E20="","",MAX(0,G20-J20))
E21: =IF(18>$C$6,"",18) | F21: =IF(E21="","",EDATE($C$7,E21-1)) | G21: =IF(E21="","",K20) | H21: =IF(E21="","",$C$9) | I21: =IF(E21="","",-IPMT($C$5/12,E21,$C$6,$C$4)) | J21: =IF(E21="","",-PPMT($C$5/12,E21,$C$6,$C$4)) | K21: =IF(E21="","",MAX(0,G21-J21))
E22: =IF(19>$C$6,"",19) | F22: =IF(E22="","",EDATE($C$7,E22-1)) | G22: =IF(E22="","",K21) | H22: =IF(E22="","",$C$9) | I22: =IF(E22="","",-IPMT($C$5/12,E22,$C$6,$C$4)) | J22: =IF(E22="","",-PPMT($C$5/12,E22,$C$6,$C$4)) | K22: =IF(E22="","",MAX(0,G22-J22))
E23: =IF(20>$C$6,"",20) | F23: =IF(E23="","",EDATE($C$7,E23-1)) | G23: =IF(E23="","",K22) | H23: =IF(E23="","",$C$9) | I23: =IF(E23="","",-IPMT($C$5/12,E23,$C$6,$C$4)) | J23: =IF(E23="","",-PPMT($C$5/12,E23,$C$6,$C$4)) | K23: =IF(E23="","",MAX(0,G23-J23))
E24: =IF(21>$C$6,"",21) | F24: =IF(E24="","",EDATE($C$7,E24-1)) | G24: =IF(E24="","",K23) | H24: =IF(E24="","",$C$9) | I24: =IF(E24="","",-IPMT($C$5/12,E24,$C$6,$C$4)) | J24: =IF(E24="","",-PPMT($C$5/12,E24,$C$6,$C$4)) | K24: =IF(E24="","",MAX(0,G24-J24))
E25: =IF(22>$C$6,"",22) | F25: =IF(E25="","",EDATE($C$7,E25-1)) | G25: =IF(E25="","",K24) | H25: =IF(E25="","",$C$9) | I25: =IF(E25="","",-IPMT($C$5/12,E25,$C$6,$C$4)) | J25: =IF(E25="","",-PPMT($C$5/12,E25,$C$6,$C$4)) | K25: =IF(E25="","",MAX(0,G25-J25))
E26: =IF(23>$C$6,"",23) | F26: =IF(E26="","",EDATE($C$7,E26-1)) | G26: =IF(E26="","",K25) | H26: =IF(E26="","",$C$9) | I26: =IF(E26="","",-IPMT($C$5/12,E26,$C$6,$C$4)) | J26: =IF(E26="","",-PPMT($C$5/12,E26,$C$6,$C$4)) | K26: =IF(E26="","",MAX(0,G26-J26))
E27: =IF(24>$C$6,"",24) | F27: =IF(E27="","",EDATE($C$7,E27-1)) | G27: =IF(E27="","",K26) | H27: =IF(E27="","",$C$9) | I27: =IF(E27="","",-IPMT($C$5/12,E27,$C$6,$C$4)) | J27: =IF(E27="","",-PPMT($C$5/12,E27,$C$6,$C$4)) | K27: =IF(E27="","",MAX(0,G27-J27))
E28: =IF(25>$C$6,"",25) | F28: =IF(E28="","",EDATE($C$7,E28-1)) | G28: =IF(E28="","",K27) | H28: =IF(E28="","",$C$9) | I28: =IF(E28="","",-IPMT($C$5/12,E28,$C$6,$C$4)) | J28: =IF(E28="","",-PPMT($C$5/12,E28,$C$6,$C$4)) | K28: =IF(E28="","",MAX(0,G28-J28))
E29: =IF(26>$C$6,"",26) | F29: =IF(E29="","",EDATE($C$7,E29-1)) | G29: =IF(E29="","",K28) | H29: =IF(E29="","",$C$9) | I29: =IF(E29="","",-IPMT($C$5/12,E29,$C$6,$C$4)) | J29: =IF(E29="","",-PPMT($C$5/12,E29,$C$6,$C$4)) | K29: =IF(E29="","",MAX(0,G29-J29))
E30: =IF(27>$C$6,"",27) | F30: =IF(E30="","",EDATE($C$7,E30-1)) | G30: =IF(E30="","",K29) | H30: =IF(E30="","",$C$9) | I30: =IF(E30="","",-IPMT($C$5/12,E30,$C$6,$C$4)) | J30: =IF(E30="","",-PPMT($C$5/12,E30,$C$6,$C$4)) | K30: =IF(E30="","",MAX(0,G30-J30))
E31: =IF(28>$C$6,"",28) | F31: =IF(E31="","",EDATE($C$7,E31-1)) | G31: =IF(E31="","",K30) | H31: =IF(E31="","",$C$9) | I31: =IF(E31="","",-IPMT($C$5/12,E31,$C$6,$C$4)) | J31: =IF(E31="","",-PPMT($C$5/12,E31,$C$6,$C$4)) | K31: =IF(E31="","",MAX(0,G31-J31))
E32: =IF(29>$C$6,"",29) | F32: =IF(E32="","",EDATE($C$7,E32-1)) | G32: =IF(E32="","",K31) | H32: =IF(E32="","",$C$9) | I32: =IF(E32="","",-IPMT($C$5/12,E32,$C$6,$C$4)) | J32: =IF(E32="","",-PPMT($C$5/12,E32,$C$6,$C$4)) | K32: =IF(E32="","",MAX(0,G32-J32))
E33: =IF(30>$C$6,"",30) | F33: =IF(E33="","",EDATE($C$7,E33-1)) | G33: =IF(E33="","",K32) | H33: =IF(E33="","",$C$9) | I33: =IF(E33="","",-IPMT($C$5/12,E33,$C$6,$C$4)) | J33: =IF(E33="","",-PPMT($C$5/12,E33,$C$6,$C$4)) | K33: =IF(E33="","",MAX(0,G33-J33))
E34: =IF(31>$C$6,"",31) | F34: =IF(E34="","",EDATE($C$7,E34-1)) | G34: =IF(E34="","",K33) | H34: =IF(E34="","",$C$9) | I34: =IF(E34="","",-IPMT($C$5/12,E34,$C$6,$C$4)) | J34: =IF(E34="","",-PPMT($C$5/12,E34,$C$6,$C$4)) | K34: =IF(E34="","",MAX(0,G34-J34))
E35: =IF(32>$C$6,"",32) | F35: =IF(E35="","",EDATE($C$7,E35-1)) | G35: =IF(E35="","",K34) | H35: =IF(E35="","",$C$9) | I35: =IF(E35="","",-IPMT($C$5/12,E35,$C$6,$C$4)) | J35: =IF(E35="","",-PPMT($C$5/12,E35,$C$6,$C$4)) | K35: =IF(E35="","",MAX(0,G35-J35))
E36: =IF(33>$C$6,"",33) | F36: =IF(E36="","",EDATE($C$7,E36-1)) | G36: =IF(E36="","",K35) | H36: =IF(E36="","",$C$9) | I36: =IF(E36="","",-IPMT($C$5/12,E36,$C$6,$C$4)) | J36: =IF(E36="","",-PPMT($C$5/12,E36,$C$6,$C$4)) | K36: =IF(E36="","",MAX(0,G36-J36))
E37: =IF(34>$C$6,"",34) | F37: =IF(E37="","",EDATE($C$7,E37-1)) | G37: =IF(E37="","",K36) | H37: =IF(E37="","",$C$9) | I37: =IF(E37="","",-IPMT($C$5/12,E37,$C$6,$C$4)) | J37: =IF(E37="","",-PPMT($C$5/12,E37,$C$6,$C$4)) | K37: =IF(E37="","",MAX(0,G37-J37))
E38: =IF(35>$C$6,"",35) | F38: =IF(E38="","",EDATE($C$7,E38-1)) | G38: =IF(E38="","",K37) | H38: =IF(E38="","",$C$9) | I38: =IF(E38="","",-IPMT($C$5/12,E38,$C$6,$C$4)) | J38: =IF(E38="","",-PPMT($C$5/12,E38,$C$6,$C$4)) | K38: =IF(E38="","",MAX(0,G38-J38))
E39: =IF(36>$C$6,"",36) | F39: =IF(E39="","",EDATE($C$7,E39-1)) | G39: =IF(E39="","",K38) | H39: =IF(E39="","",$C$9) | I39: =IF(E39="","",-IPMT($C$5/12,E39,$C$6,$C$4)) | J39: =IF(E39="","",-PPMT($C$5/12,E39,$C$6,$C$4)) | K39: =IF(E39="","",MAX(0,G39-J39))
E40: =IF(37>$C$6,"",37) | F40: =IF(E40="","",EDATE($C$7,E40-1)) | G40: =IF(E40="","",K39) | H40: =IF(E40="","",$C$9) | I40: =IF(E40="","",-IPMT($C$5/12,E40,$C$6,$C$4)) | J40: =IF(E40="","",-PPMT($C$5/12,E40,$C$6,$C$4)) | K40: =IF(E40="","",MAX(0,G40-J40))
E41: =IF(38>$C$6,"",38) | F41: =IF(E41="","",EDATE($C$7,E41-1)) | G41: =IF(E41="","",K40) | H41: =IF(E41="","",$C$9) | I41: =IF(E41="","",-IPMT($C$5/12,E41,$C$6,$C$4)) | J41: =IF(E41="","",-PPMT($C$5/12,E41,$C$6,$C$4)) | K41: =IF(E41="","",MAX(0,G41-J41))
E42: =IF(39>$C$6,"",39) | F42: =IF(E42="","",EDATE($C$7,E42-1)) | G42: =IF(E42="","",K41) | H42: =IF(E42="","",$C$9) | I42: =IF(E42="","",-IPMT($C$5/12,E42,$C$6,$C$4)) | J42: =IF(E42="","",-PPMT($C$5/12,E42,$C$6,$C$4)) | K42: =IF(E42="","",MAX(0,G42-J42))
E43: =IF(40>$C$6,"",40) | F43: =IF(E43="","",EDATE($C$7,E43-1)) | G43: =IF(E43="","",K42) | H43: =IF(E43="","",$C$9) | I43: =IF(E43="","",-IPMT($C$5/12,E43,$C$6,$C$4)) | J43: =IF(E43="","",-PPMT($C$5/12,E43,$C$6,$C$4)) | K43: =IF(E43="","",MAX(0,G43-J43))
E44: =IF(41>$C$6,"",41) | F44: =IF(E44="","",EDATE($C$7,E44-1)) | G44: =IF(E44="","",K43) | H44: =IF(E44="","",$C$9) | I44: =IF(E44="","",-IPMT($C$5/12,E44,$C$6,$C$4)) | J44: =IF(E44="","",-PPMT($C$5/12,E44,$C$6,$C$4)) | K44: =IF(E44="","",MAX(0,G44-J44))
E45: =IF(42>$C$6,"",42) | F45: =IF(E45="","",EDATE($C$7,E45-1)) | G45: =IF(E45="","",K44) | H45: =IF(E45="","",$C$9) | I45: =IF(E45="","",-IPMT($C$5/12,E45,$C$6,$C$4)) | J45: =IF(E45="","",-PPMT($C$5/12,E45,$C$6,$C$4)) | K45: =IF(E45="","",MAX(0,G45-J45))
E46: =IF(43>$C$6,"",43) | F46: =IF(E46="","",EDATE($C$7,E46-1)) | G46: =IF(E46="","",K45) | H46: =IF(E46="","",$C$9) | I46: =IF(E46="","",-IPMT($C$5/12,E46,$C$6,$C$4)) | J46: =IF(E46="","",-PPMT($C$5/12,E46,$C$6,$C$4)) | K46: =IF(E46="","",MAX(0,G46-J46))
E47: =IF(44>$C$6,"",44) | F47: =IF(E47="","",EDATE($C$7,E47-1)) | G47: =IF(E47="","",K46) | H47: =IF(E47="","",$C$9) | I47: =IF(E47="","",-IPMT($C$5/12,E47,$C$6,$C$4)) | J47: =IF(E47="","",-PPMT($C$5/12,E47,$C$6,$C$4)) | K47: =IF(E47="","",MAX(0,G47-J47))
E48: =IF(45>$C$6,"",45) | F48: =IF(E48="","",EDATE($C$7,E48-1)) | G48: =IF(E48="","",K47) | H48: =IF(E48="","",$C$9) | I48: =IF(E48="","",-IPMT($C$5/12,E48,$C$6,$C$4)) | J48: =IF(E48="","",-PPMT($C$5/12,E48,$C$6,$C$4)) | K48: =IF(E48="","",MAX(0,G48-J48))
E49: =IF(46>$C$6,"",46) | F49: =IF(E49="","",EDATE($C$7,E49-1)) | G49: =IF(E49="","",K48) | H49: =IF(E49="","",$C$9) | I49: =IF(E49="","",-IPMT($C$5/12,E49,$C$6,$C$4)) | J49: =IF(E49="","",-PPMT($C$5/12,E49,$C$6,$C$4)) | K49: =IF(E49="","",MAX(0,G49-J49))
E50: =IF(47>$C$6,"",47) | F50: =IF(E50="","",EDATE($C$7,E50-1)) | G50: =IF(E50="","",K49) | H50: =IF(E50="","",$C$9) | I50: =IF(E50="","",-IPMT($C$5/12,E50,$C$6,$C$4)) | J50: =IF(E50="","",-PPMT($C$5/12,E50,$C$6,$C$4)) | K50: =IF(E50="","",MAX(0,G50-J50))
E51: =IF(48>$C$6,"",48) | F51: =IF(E51="","",EDATE($C$7,E51-1)) | G51: =IF(E51="","",K50) | H51: =IF(E51="","",$C$9) | I51: =IF(E51="","",-IPMT($C$5/12,E51,$C$6,$C$4)) | J51: =IF(E51="","",-PPMT($C$5/12,E51,$C$6,$C$4)) | K51: =IF(E51="","",MAX(0,G51-J51))
E52: =IF(49>$C$6,"",49) | F52: =IF(E52="","",EDATE($C$7,E52-1)) | G52: =IF(E52="","",K51) | H52: =IF(E52="","",$C$9) | I52: =IF(E52="","",-IPMT($C$5/12,E52,$C$6,$C$4)) | J52: =IF(E52="","",-PPMT($C$5/12,E52,$C$6,$C$4)) | K52: =IF(E52="","",MAX(0,G52-J52))
E53: =IF(50>$C$6,"",50) | F53: =IF(E53="","",EDATE($C$7,E53-1)) | G53: =IF(E53="","",K52) | H53: =IF(E53="","",$C$9) | I53: =IF(E53="","",-IPMT($C$5/12,E53,$C$6,$C$4)) | J53: =IF(E53="","",-PPMT($C$5/12,E53,$C$6,$C$4)) | K53: =IF(E53="","",MAX(0,G53-J53))
E54: =IF(51>$C$6,"",51) | F54: =IF(E54="","",EDATE($C$7,E54-1)) | G54: =IF(E54="","",K53) | H54: =IF(E54="","",$C$9) | I54: =IF(E54="","",-IPMT($C$5/12,E54,$C$6,$C$4)) | J54: =IF(E54="","",-PPMT($C$5/12,E54,$C$6,$C$4)) | K54: =IF(E54="","",MAX(0,G54-J54))
E55: =IF(52>$C$6,"",52) | F55: =IF(E55="","",EDATE($C$7,E55-1)) | G55: =IF(E55="","",K54) | H55: =IF(E55="","",$C$9) | I55: =IF(E55="","",-IPMT($C$5/12,E55,$C$6,$C$4)) | J55: =IF(E55="","",-PPMT($C$5/12,E55,$C$6,$C$4)) | K55: =IF(E55="","",MAX(0,G55-J55))
E56: =IF(53>$C$6,"",53) | F56: =IF(E56="","",EDATE($C$7,E56-1)) | G56: =IF(E56="","",K55) | H56: =IF(E56="","",$C$9) | I56: =IF(E56="","",-IPMT($C$5/12,E56,$C$6,$C$4)) | J56: =IF(E56="","",-PPMT($C$5/12,E56,$C$6,$C$4)) | K56: =IF(E56="","",MAX(0,G56-J56))
E57: =IF(54>$C$6,"",54) | F57: =IF(E57="","",EDATE($C$7,E57-1)) | G57: =IF(E57="","",K56) | H57: =IF(E57="","",$C$9) | I57: =IF(E57="","",-IPMT($C$5/12,E57,$C$6,$C$4)) | J57: =IF(E57="","",-PPMT($C$5/12,E57,$C$6,$C$4)) | K57: =IF(E57="","",MAX(0,G57-J57))
E58: =IF(55>$C$6,"",55) | F58: =IF(E58="","",EDATE($C$7,E58-1)) | G58: =IF(E58="","",K57) | H58: =IF(E58="","",$C$9) | I58: =IF(E58="","",-IPMT($C$5/12,E58,$C$6,$C$4)) | J58: =IF(E58="","",-PPMT($C$5/12,E58,$C$6,$C$4)) | K58: =IF(E58="","",MAX(0,G58-J58))
E59: =IF(56>$C$6,"",56) | F59: =IF(E59="","",EDATE($C$7,E59-1)) | G59: =IF(E59="","",K58) | H59: =IF(E59="","",$C$9) | I59: =IF(E59="","",-IPMT($C$5/12,E59,$C$6,$C$4)) | J59: =IF(E59="","",-PPMT($C$5/12,E59,$C$6,$C$4)) | K59: =IF(E59="","",MAX(0,G59-J59))
E60: =IF(57>$C$6,"",57) | F60: =IF(E60="","",EDATE($C$7,E60-1)) | G60: =IF(E60="","",K59) | H60: =IF(E60="","",$C$9) | I60: =IF(E60="","",-IPMT($C$5/12,E60,$C$6,$C$4)) | J60: =IF(E60="","",-PPMT($C$5/12,E60,$C$6,$C$4)) | K60: =IF(E60="","",MAX(0,G60-J60))
E61: =IF(58>$C$6,"",58) | F61: =IF(E61="","",EDATE($C$7,E61-1)) | G61: =IF(E61="","",K60) | H61: =IF(E61="","",$C$9) | I61: =IF(E61="","",-IPMT($C$5/12,E61,$C$6,$C$4)) | J61: =IF(E61="","",-PPMT($C$5/12,E61,$C$6,$C$4)) | K61: =IF(E61="","",MAX(0,G61-J61))
E62: =IF(59>$C$6,"",59) | F62: =IF(E62="","",EDATE($C$7,E62-1)) | G62: =IF(E62="","",K61) | H62: =IF(E62="","",$C$9) | I62: =IF(E62="","",-IPMT($C$5/12,E62,$C$6,$C$4)) | J62: =IF(E62="","",-PPMT($C$5/12,E62,$C$6,$C$4)) | K62: =IF(E62="","",MAX(0,G62-J62))
E63: =IF(60>$C$6,"",60) | F63: =IF(E63="","",EDATE($C$7,E63-1)) | G63: =IF(E63="","",K62) | H63: =IF(E63="","",$C$9) | I63: =IF(E63="","",-IPMT($C$5/12,E63,$C$6,$C$4)) | J63: =IF(E63="","",-PPMT($C$5/12,E63,$C$6,$C$4)) | K63: =IF(E63="","",MAX(0,G63-J63))
E64: =IF(61>$C$6,"",61) | F64: =IF(E64="","",EDATE($C$7,E64-1)) | G64: =IF(E64="","",K63) | H64: =IF(E64="","",$C$9) | I64: =IF(E64="","",-IPMT($C$5/12,E64,$C$6,$C$4)) | J64: =IF(E64="","",-PPMT($C$5/12,E64,$C$6,$C$4)) | K64: =IF(E64="","",MAX(0,G64-J64))
E65: =IF(62>$C$6,"",62) | F65: =IF(E65="","",EDATE($C$7,E65-1)) | G65: =IF(E65="","",K64) | H65: =IF(E65="","",$C$9) | I65: =IF(E65="","",-IPMT($C$5/12,E65,$C$6,$C$4)) | J65: =IF(E65="","",-PPMT($C$5/12,E65,$C$6,$C$4)) | K65: =IF(E65="","",MAX(0,G65-J65))
E66: =IF(63>$C$6,"",63) | F66: =IF(E66="","",EDATE($C$7,E66-1)) | G66: =IF(E66="","",K65) | H66: =IF(E66="","",$C$9) | I66: =IF(E66="","",-IPMT($C$5/12,E66,$C$6,$C$4)) | J66: =IF(E66="","",-PPMT($C$5/12,E66,$C$6,$C$4)) | K66: =IF(E66="","",MAX(0,G66-J66))
E67: =IF(64>$C$6,"",64) | F67: =IF(E67="","",EDATE($C$7,E67-1)) | G67: =IF(E67="","",K66) | H67: =IF(E67="","",$C$9) | I67: =IF(E67="","",-IPMT($C$5/12,E67,$C$6,$C$4)) | J67: =IF(E67="","",-PPMT($C$5/12,E67,$C$6,$C$4)) | K67: =IF(E67="","",MAX(0,G67-J67))
E68: =IF(65>$C$6,"",65) | F68: =IF(E68="","",EDATE($C$7,E68-1)) | G68: =IF(E68="","",K67) | H68: =IF(E68="","",$C$9) | I68: =IF(E68="","",-IPMT($C$5/12,E68,$C$6,$C$4)) | J68: =IF(E68="","",-PPMT($C$5/12,E68,$C$6,$C$4)) | K68: =IF(E68="","",MAX(0,G68-J68))
E69: =IF(66>$C$6,"",66) | F69: =IF(E69="","",EDATE($C$7,E69-1)) | G69: =IF(E69="","",K68) | H69: =IF(E69="","",$C$9) | I69: =IF(E69="","",-IPMT($C$5/12,E69,$C$6,$C$4)) | J69: =IF(E69="","",-PPMT($C$5/12,E69,$C$6,$C$4)) | K69: =IF(E69="","",MAX(0,G69-J69))
E70: =IF(67>$C$6,"",67) | F70: =IF(E70="","",EDATE($C$7,E70-1)) | G70: =IF(E70="","",K69) | H70: =IF(E70="","",$C$9) | I70: =IF(E70="","",-IPMT($C$5/12,E70,$C$6,$C$4)) | J70: =IF(E70="","",-PPMT($C$5/12,E70,$C$6,$C$4)) | K70: =IF(E70="","",MAX(0,G70-J70))
E71: =IF(68>$C$6,"",68) | F71: =IF(E71="","",EDATE($C$7,E71-1)) | G71: =IF(E71="","",K70) | H71: =IF(E71="","",$C$9) | I71: =IF(E71="","",-IPMT($C$5/12,E71,$C$6,$C$4)) | J71: =IF(E71="","",-PPMT($C$5/12,E71,$C$6,$C$4)) | K71: =IF(E71="","",MAX(0,G71-J71))
E72: =IF(69>$C$6,"",69) | F72: =IF(E72="","",EDATE($C$7,E72-1)) | G72: =IF(E72="","",K71) | H72: =IF(E72="","",$C$9) | I72: =IF(E72="","",-IPMT($C$5/12,E72,$C$6,$C$4)) | J72: =IF(E72="","",-PPMT($C$5/12,E72,$C$6,$C$4)) | K72: =IF(E72="","",MAX(0,G72-J72))
E73: =IF(70>$C$6,"",70) | F73: =IF(E73="","",EDATE($C$7,E73-1)) | G73: =IF(E73="","",K72) | H73: =IF(E73="","",$C$9) | I73: =IF(E73="","",-IPMT($C$5/12,E73,$C$6,$C$4)) | J73: =IF(E73="","",-PPMT($C$5/12,E73,$C$6,$C$4)) | K73: =IF(E73="","",MAX(0,G73-J73))
E74: =IF(71>$C$6,"",71) | F74: =IF(E74="","",EDATE($C$7,E74-1)) | G74: =IF(E74="","",K73) | H74: =IF(E74="","",$C$9) | I74: =IF(E74="","",-IPMT($C$5/12,E74,$C$6,$C$4)) | J74: =IF(E74="","",-PPMT($C$5/12,E74,$C$6,$C$4)) | K74: =IF(E74="","",MAX(0,G74-J74))
E75: =IF(72>$C$6,"",72) | F75: =IF(E75="","",EDATE($C$7,E75-1)) | G75: =IF(E75="","",K74) | H75: =IF(E75="","",$C$9) | I75: =IF(E75="","",-IPMT($C$5/12,E75,$C$6,$C$4)) | J75: =IF(E75="","",-PPMT($C$5/12,E75,$C$6,$C$4)) | K75: =IF(E75="","",MAX(0,G75-J75))
E76: =IF(73>$C$6,"",73) | F76: =IF(E76="","",EDATE($C$7,E76-1)) | G76: =IF(E76="","",K75) | H76: =IF(E76="","",$C$9) | I76: =IF(E76="","",-IPMT($C$5/12,E76,$C$6,$C$4)) | J76: =IF(E76="","",-PPMT($C$5/12,E76,$C$6,$C$4)) | K76: =IF(E76="","",MAX(0,G76-J76))
E77: =IF(74>$C$6,"",74) | F77: =IF(E77="","",EDATE($C$7,E77-1)) | G77: =IF(E77="","",K76) | H77: =IF(E77="","",$C$9) | I77: =IF(E77="","",-IPMT($C$5/12,E77,$C$6,$C$4)) | J77: =IF(E77="","",-PPMT($C$5/12,E77,$C$6,$C$4)) | K77: =IF(E77="","",MAX(0,G77-J77))
E78: =IF(75>$C$6,"",75) | F78: =IF(E78="","",EDATE($C$7,E78-1)) | G78: =IF(E78="","",K77) | H78: =IF(E78="","",$C$9) | I78: =IF(E78="","",-IPMT($C$5/12,E78,$C$6,$C$4)) | J78: =IF(E78="","",-PPMT($C$5/12,E78,$C$6,$C$4)) | K78: =IF(E78="","",MAX(0,G78-J78))
E79: =IF(76>$C$6,"",76) | F79: =IF(E79="","",EDATE($C$7,E79-1)) | G79: =IF(E79="","",K78) | H79: =IF(E79="","",$C$9) | I79: =IF(E79="","",-IPMT($C$5/12,E79,$C$6,$C$4)) | J79: =IF(E79="","",-PPMT($C$5/12,E79,$C$6,$C$4)) | K79: =IF(E79="","",MAX(0,G79-J79))
E80: =IF(77>$C$6,"",77) | F80: =IF(E80="","",EDATE($C$7,E80-1)) | G80: =IF(E80="","",K79) | H80: =IF(E80="","",$C$9) | I80: =IF(E80="","",-IPMT($C$5/12,E80,$C$6,$C$4)) | J80: =IF(E80="","",-PPMT($C$5/12,E80,$C$6,$C$4)) | K80: =IF(E80="","",MAX(0,G80-J80))
E81: =IF(78>$C$6,"",78) | F81: =IF(E81="","",EDATE($C$7,E81-1)) | G81: =IF(E81="","",K80) | H81: =IF(E81="","",$C$9) | I81: =IF(E81="","",-IPMT($C$5/12,E81,$C$6,$C$4)) | J81: =IF(E81="","",-PPMT($C$5/12,E81,$C$6,$C$4)) | K81: =IF(E81="","",MAX(0,G81-J81))
E82: =IF(79>$C$6,"",79) | F82: =IF(E82="","",EDATE($C$7,E82-1)) | G82: =IF(E82="","",K81) | H82: =IF(E82="","",$C$9) | I82: =IF(E82="","",-IPMT($C$5/12,E82,$C$6,$C$4)) | J82: =IF(E82="","",-PPMT($C$5/12,E82,$C$6,$C$4)) | K82: =IF(E82="","",MAX(0,G82-J82))
E83: =IF(80>$C$6,"",80) | F83: =IF(E83="","",EDATE($C$7,E83-1)) | G83: =IF(E83="","",K82) | H83: =IF(E83="","",$C$9) | I83: =IF(E83="","",-IPMT($C$5/12,E83,$C$6,$C$4)) | J83: =IF(E83="","",-PPMT($C$5/12,E83,$C$6,$C$4)) | K83: =IF(E83="","",MAX(0,G83-J83))
E84: =IF(81>$C$6,"",81) | F84: =IF(E84="","",EDATE($C$7,E84-1)) | G84: =IF(E84="","",K83) | H84: =IF(E84="","",$C$9) | I84: =IF(E84="","",-IPMT($C$5/12,E84,$C$6,$C$4)) | J84: =IF(E84="","",-PPMT($C$5/12,E84,$C$6,$C$4)) | K84: =IF(E84="","",MAX(0,G84-J84))
E85: =IF(82>$C$6,"",82) | F85: =IF(E85="","",EDATE($C$7,E85-1)) | G85: =IF(E85="","",K84) | H85: =IF(E85="","",$C$9) | I85: =IF(E85="","",-IPMT($C$5/12,E85,$C$6,$C$4)) | J85: =IF(E85="","",-PPMT($C$5/12,E85,$C$6,$C$4)) | K85: =IF(E85="","",MAX(0,G85-J85))
E86: =IF(83>$C$6,"",83) | F86: =IF(E86="","",EDATE($C$7,E86-1)) | G86: =IF(E86="","",K85) | H86: =IF(E86="","",$C$9) | I86: =IF(E86="","",-IPMT($C$5/12,E86,$C$6,$C$4)) | J86: =IF(E86="","",-PPMT($C$5/12,E86,$C$6,$C$4)) | K86: =IF(E86="","",MAX(0,G86-J86))
E87: =IF(84>$C$6,"",84) | F87: =IF(E87="","",EDATE($C$7,E87-1)) | G87: =IF(E87="","",K86) | H87: =IF(E87="","",$C$9) | I87: =IF(E87="","",-IPMT($C$5/12,E87,$C$6,$C$4)) | J87: =IF(E87="","",-PPMT($C$5/12,E87,$C$6,$C$4)) | K87: =IF(E87="","",MAX(0,G87-J87))
E88: =IF(85>$C$6,"",85) | F88: =IF(E88="","",EDATE($C$7,E88-1)) | G88: =IF(E88="","",K87) | H88: =IF(E88="","",$C$9) | I88: =IF(E88="","",-IPMT($C$5/12,E88,$C$6,$C$4)) | J88: =IF(E88="","",-PPMT($C$5/12,E88,$C$6,$C$4)) | K88: =IF(E88="","",MAX(0,G88-J88))
E89: =IF(86>$C$6,"",86) | F89: =IF(E89="","",EDATE($C$7,E89-1)) | G89: =IF(E89="","",K88) | H89: =IF(E89="","",$C$9) | I89: =IF(E89="","",-IPMT($C$5/12,E89,$C$6,$C$4)) | J89: =IF(E89="","",-PPMT($C$5/12,E89,$C$6,$C$4)) | K89: =IF(E89="","",MAX(0,G89-J89))
E90: =IF(87>$C$6,"",87) | F90: =IF(E90="","",EDATE($C$7,E90-1)) | G90: =IF(E90="","",K89) | H90: =IF(E90="","",$C$9) | I90: =IF(E90="","",-IPMT($C$5/12,E90,$C$6,$C$4)) | J90: =IF(E90="","",-PPMT($C$5/12,E90,$C$6,$C$4)) | K90: =IF(E90="","",MAX(0,G90-J90))
E91: =IF(88>$C$6,"",88) | F91: =IF(E91="","",EDATE($C$7,E91-1)) | G91: =IF(E91="","",K90) | H91: =IF(E91="","",$C$9) | I91: =IF(E91="","",-IPMT($C$5/12,E91,$C$6,$C$4)) | J91: =IF(E91="","",-PPMT($C$5/12,E91,$C$6,$C$4)) | K91: =IF(E91="","",MAX(0,G91-J91))
E92: =IF(89>$C$6,"",89) | F92: =IF(E92="","",EDATE($C$7,E92-1)) | G92: =IF(E92="","",K91) | H92: =IF(E92="","",$C$9) | I92: =IF(E92="","",-IPMT($C$5/12,E92,$C$6,$C$4)) | J92: =IF(E92="","",-PPMT($C$5/12,E92,$C$6,$C$4)) | K92: =IF(E92="","",MAX(0,G92-J92))
E93: =IF(90>$C$6,"",90) | F93: =IF(E93="","",EDATE($C$7,E93-1)) | G93: =IF(E93="","",K92) | H93: =IF(E93="","",$C$9) | I93: =IF(E93="","",-IPMT($C$5/12,E93,$C$6,$C$4)) | J93: =IF(E93="","",-PPMT($C$5/12,E93,$C$6,$C$4)) | K93: =IF(E93="","",MAX(0,G93-J93))
E94: =IF(91>$C$6,"",91) | F94: =IF(E94="","",EDATE($C$7,E94-1)) | G94: =IF(E94="","",K93) | H94: =IF(E94="","",$C$9) | I94: =IF(E94="","",-IPMT($C$5/12,E94,$C$6,$C$4)) | J94: =IF(E94="","",-PPMT($C$5/12,E94,$C$6,$C$4)) | K94: =IF(E94="","",MAX(0,G94-J94))
E95: =IF(92>$C$6,"",92) | F95: =IF(E95="","",EDATE($C$7,E95-1)) | G95: =IF(E95="","",K94) | H95: =IF(E95="","",$C$9) | I95: =IF(E95="","",-IPMT($C$5/12,E95,$C$6,$C$4)) | J95: =IF(E95="","",-PPMT($C$5/12,E95,$C$6,$C$4)) | K95: =IF(E95="","",MAX(0,G95-J95))
E96: =IF(93>$C$6,"",93) | F96: =IF(E96="","",EDATE($C$7,E96-1)) | G96: =IF(E96="","",K95) | H96: =IF(E96="","",$C$9) | I96: =IF(E96="","",-IPMT($C$5/12,E96,$C$6,$C$4)) | J96: =IF(E96="","",-PPMT($C$5/12,E96,$C$6,$C$4)) | K96: =IF(E96="","",MAX(0,G96-J96))
E97: =IF(94>$C$6,"",94) | F97: =IF(E97="","",EDATE($C$7,E97-1)) | G97: =IF(E97="","",K96) | H97: =IF(E97="","",$C$9) | I97: =IF(E97="","",-IPMT($C$5/12,E97,$C$6,$C$4)) | J97: =IF(E97="","",-PPMT($C$5/12,E97,$C$6,$C$4)) | K97: =IF(E97="","",MAX(0,G97-J97))
E98: =IF(95>$C$6,"",95) | F98: =IF(E98="","",EDATE($C$7,E98-1)) | G98: =IF(E98="","",K97) | H98: =IF(E98="","",$C$9) | I98: =IF(E98="","",-IPMT($C$5/12,E98,$C$6,$C$4)) | J98: =IF(E98="","",-PPMT($C$5/12,E98,$C$6,$C$4)) | K98: =IF(E98="","",MAX(0,G98-J98))
E99: =IF(96>$C$6,"",96) | F99: =IF(E99="","",EDATE($C$7,E99-1)) | G99: =IF(E99="","",K98) | H99: =IF(E99="","",$C$9) | I99: =IF(E99="","",-IPMT($C$5/12,E99,$C$6,$C$4)) | J99: =IF(E99="","",-PPMT($C$5/12,E99,$C$6,$C$4)) | K99: =IF(E99="","",MAX(0,G99-J99))
E100: =IF(97>$C$6,"",97) | F100: =IF(E100="","",EDATE($C$7,E100-1)) | G100: =IF(E100="","",K99) | H100: =IF(E100="","",$C$9) | I100: =IF(E100="","",-IPMT($C$5/12,E100,$C$6,$C$4)) | J100: =IF(E100="","",-PPMT($C$5/12,E100,$C$6,$C$4)) | K100: =IF(E100="","",MAX(0,G100-J100))
E101: =IF(98>$C$6,"",98) | F101: =IF(E101="","",EDATE($C$7,E101-1)) | G101: =IF(E101="","",K100) | H101: =IF(E101="","",$C$9) | I101: =IF(E101="","",-IPMT($C$5/12,E101,$C$6,$C$4)) | J101: =IF(E101="","",-PPMT($C$5/12,E101,$C$6,$C$4)) | K101: =IF(E101="","",MAX(0,G101-J101))
...

Sheet Assumptions
B2: Model Assumptions
B4: As-of (reporting) date | C4: 46203
B6: Asset Classification & Provisioning (by DPD) | H6: Risk Grade by CIBIL
B7: DPD From | C7: Bucket | D7: Asset Class | E7: NPA? | F7: Provision % | H7: CIBIL From | I7: Grade
B8: 0 | C8: Current | D8: Standard | E8: No | F8: 0.004 | H8: 300 | I8: D - High Risk
B9: 1 | C9: SMA-0 | D9: Standard | E9: No | F9: 0.004 | H9: 650 | I9: C - Watch
B10: 31 | C10: SMA-1 | D10: Standard | E10: No | F10: 0.004 | H10: 700 | I10: B - Moderate
B11: 61 | C11: SMA-2 | D11: Standard | E11: No | F11: 0.004 | H11: 750 | I11: A - Prime
B12: 91 | C12: Sub-standard | D12: NPA | E12: Yes | F12: 0.15
B13: 366 | C13: Doubtful | D13: NPA | E13: Yes | F13: 0.4 | H13: Source: model convention (bands chosen by analyst).
B14: 731 | C14: Loss | D14: NPA | E14: Yes | F14: 1
B16: Source: simplified from RBI Master Circular on IRACP norms (SMA classification & NPA at 90+ DPD). Doubtful provision blended at 40%; illustrative only.

Sheet Branches
A1: Branch | B1: City | C1: Region
A2: BLR-01 | B2: Bengaluru | C2: South
A3: CHN-01 | B3: Chennai | C3: South
A4: HYD-01 | B4: Hyderabad | C4: South
A5: KOC-01 | B5: Kochi | C5: South
A6: MUM-01 | B6: Mumbai | C6: West
A7: PUN-01 | B7: Pune | C7: West
A8: AMD-01 | B8: Ahmedabad | C8: West
A9: DEL-01 | B9: New Delhi | C9: North
A10: LKO-01 | B10: Lucknow | C10: North
A11: JAI-01 | B11: Jaipur | C11: North
A12: KOL-01 | B12: Kolkata | C12: East
... A15: GUW-01 | B15: Guwahati | C15: East
